lab1/D_FF.v
module D_FF (q, d, reset, clk);
  output reg q;
  input d, reset, clk;

  always @(posedge clk)
  if (reset)
    q <= 0;  // On reset, set to 0
  else
    q <= d; // Otherwise out = d
endmodule

lab1/register.v
`include "D_FF.v"

module register (in, out, en, clk);
	output [63:0] out;

	input [63:0] in;
	input en, clk;

	wire [63:0] temp, old;

	assign old = out;
	generate
		genvar i; 
		for (i = 0; i < 64; i = i + 1'b1) begin : set
			mux2to1 choose (.new(in[i]), .old(old[i]), .out(temp[i]), .en(en));
			D_FF set (.q(out[i]), .d(temp[i]), .reset(1'b0), .clk(clk));
		end
	endgenerate
endmodule

module mux2to1 (new, old, out, en);
	output wire out;

	input new, old, en;

	wire ren;
	wire [1:0] con;

	not ren0 (ren, en);

	and con0 (con[0], en, new);
	and con1 (con[1], ren, old);
	
	or out0 (out, con[0], con[1]);
	
	//assign out = (en & new) | (~en & old);

endmodule

lab1/tb_register.v
`include "register.v"

module tb_register();
	reg [63:0] in;
	wire [63:0] out;
	reg en, clk;

	parameter ClockDelay = 5000;

	register dut (in, out, en, clk);

	initial begin
		$dumpfile("tb_register.vcd");
		$dumpvars(1, dut);
	end

	initial begin // Set up the clock
		clk <= 0;
		forever #(ClockDelay/2) clk <= ~clk;
	end


	integer i;
	initial begin
		en <= 1;
		for (i = 0; i < 10; i = i + 1) begin
			in <= i*64'h0000010204080001;
			@(posedge clk);
		end
		en <= 0;
		for (i = 0; i < 10; i = i + 1) begin
			in <= i*64'h0000010204080001;
			@(posedge clk);
		end
		$stop;
	end
endmodule

lab1/tb_register.vcd
$date
	Thu Jan 18 14:21:07 2018
$end
$version
	Icarus Verilog
$end
$timescale
	1s
$end
$scope module tb_register $end
$scope module dut $end
$var wire 1 ! clk $end
$var wire 1 " en $end
$var wire 64 # in [63:0] $end
$var wire 64 $ old [63:0] $end
$var wire 64 % temp [63:0] $end
$var wire 64 & out [63:0] $end
$upscope $end
$upscope $end
$enddefinitions $end
#0
$dumpvars
bx &
b0 %
bx $
b0 #
1"
0!
$end
#2500
b10000001000000100000010000000000000000001 %
b0 $
b0 &
b10000001000000100000010000000000000000001 #
1!
#5000
0!
#7500
b100000010000001000000100000000000000000010 %
b100000010000001000000100000000000000000010 #
b10000001000000100000010000000000000000001 $
b10000001000000100000010000000000000000001 &
1!
#10000
0!
#12500
b110000011000001100000110000000000000000011 %
b100000010000001000000100000000000000000010 $
b100000010000001000000100000000000000000010 &
b110000011000001100000110000000000000000011 #
1!
#15000
0!
#17500
b1000000100000010000001000000000000000000100 %
b1000000100000010000001000000000000000000100 #
b110000011000001100000110000000000000000011 $
b110000011000001100000110000000000000000011 &
1!
#20000
0!
#22500
b1010000101000010100001010000000000000000101 %
b1000000100000010000001000000000000000000100 $
b1000000100000010000001000000000000000000100 &
b1010000101000010100001010000000000000000101 #
1!
#25000
0!
#27500
b1100000110000011000001100000000000000000110 %
b1100000110000011000001100000000000000000110 #
b1010000101000010100001010000000000000000101 $
b1010000101000010100001010000000000000000101 &
1!
#30000
0!
#32500
b1110000111000011100001110000000000000000111 %
b1100000110000011000001100000000000000000110 $
b1100000110000011000001100000000000000000110 &
b1110000111000011100001110000000000000000111 #
1!
#35000
0!
#37500
b10000001000000100000010000000000000000001000 %
b10000001000000100000010000000000000000001000 #
b1110000111000011100001110000000000000000111 $
b1110000111000011100001110000000000000000111 &
1!
#40000
0!
#42500
b10010001001000100100010010000000000000001001 %
b10000001000000100000010000000000000000001000 $
b10000001000000100000010000000000000000001000 &
b10010001001000100100010010000000000000001001 #
1!
#45000
0!
#47500
b10010001001000100100010010000000000000001001 %
b0 #
0"
b10010001001000100100010010000000000000001001 $
b10010001001000100100010010000000000000001001 &
1!
#50000
0!
#52500
b10000001000000100000010000000000000000001 #
1!
#55000
0!
#57500
b100000010000001000000100000000000000000010 #
1!
#60000
0!
#62500
b110000011000001100000110000000000000000011 #
1!
#65000
0!
#67500
b1000000100000010000001000000000000000000100 #
1!
#70000
0!
#72500
b1010000101000010100001010000000000000000101 #
1!
#75000
0!
#77500
b1100000110000011000001100000000000000000110 #
1!
#80000
0!
#82500
b1110000111000011100001110000000000000000111 #
1!
#85000
0!
#87500
b10000001000000100000010000000000000000001000 #
1!
#90000
0!
#92500
b10010001001000100100010010000000000000001001 #
1!
