lab1/multiplex.v
module multiplex (in, out, read, clk, reset);
	output [63:0] out;

	input [4:0] read;
	input clk, reset;
	input [31:0][63:0] in;

	assign out = in[read];

endmodule

lab1/D_FF.v
module D_FF (q, d, reset, clk);
  output reg q;
  input d, reset, clk;

  always @(posedge clk)
  if (reset)
    q <= 0;  // On reset, set to 0
  else
    q <= d; // Otherwise out = d
endmodule

lab1/register.v
`include "D_FF.v"

module register (in, out, en, clk);
	output [63:0] out;

	input [63:0] in;
	input en, clk;

	generate
		genvar i;
		for (i = 0; i < 64; i = i + 1) begin
			D_FF hold (.q(out[i]), .d(.in[i]), .reset(0), .clk(clk));
		end
	endgenerate

endmodule

lab1/decoder.v
module decoder (in, out, en);
	output wire [31:0] out;

	input en;
	input [4:0] in;

	wire [3:0] dec;

	decoder2to4 first (.in(in[4:3]), .out(dec), .en(en));

	decoder3to8 second (.in(in[2:0]), .out(out[7:0]), .en(dec[0]));
	decoder3to8 third (.in(in[2:0]), .out(out[15:8]), .en(dec[1]));
	decoder3to8 fourth (.in(in[2:0]), .out(out[23:16]), .en(dec[2]));
	decoder3to8 fifth (.in(in[2:0]), .out(out[31:24]), .en(dec[3]));
		
endmodule

module decoder3to8 (in, out, en);
	output wire [7:0] out;

	input en;
	input [2:0] in;

	assign out[0] = ~in[0] & ~in[1] & ~in[2] & en;
	assign out[1] = in[0] & ~in[1] & ~in[2] & en;
	assign out[2] = ~in[0] & in[1] & ~in[2] & en;
	assign out[3] = in[0] & in[1] & ~in[2] & en;
	assign out[4] = ~in[0] & ~in[1] & in[2] & en;
	assign out[5] = in[0] & ~in[1] & in[2] & en;
	assign out[6] = ~in[0] & in[1] & in[2] & en;
	assign out[7] = in[0] & in[1] & in[2] & en;
endmodule


module decoder2to4 (in, out, en);
	output wire [3:0] out;

	input en;
	input [1:0] in;

	assign out[3] = in[0] & in[1] & en;
	assign out[2] = ~in[0] & in[1] & en;
	assign out[1] = in[0] & ~in[1] & en;
	assign out[0] = ~in[0] & ~in[1] & en;
endmodule

lab1/regfile.v
`include "multiplex.v"
`include "decoder.v"
`include "register.v"

module regfile (data, DRA, DRB, RA, RB, RW, en, clk);
	
	output [63:0] DRA, DRB;
	input [63:0] data;
	input [4:0] RA, RB, RW;
	input en, clk;

	wire [31:0] dec;
	wire [31:0][63:0] outwr;

	decoder start (.in(RW), .out(dec), .en(en));
	assign dec[31] = 1'b0;

	generate
		genvar i;
		for (i = 0; i < 31; i = i + 1'b1) begin
			register set (.in(data), .out(outwr[i]), .en(dec[i]), .clk(clk));
		end
	endgenerate

	multiplex one (.in(outwr), .out(DRA), .read(RA), .clk(clk), .reset(reset));
	multiplex two (.in(outwr), .out(DRB), .read(RB), .clk(clk), .reset(reset));

endmodule

lab1/regstim.v
// Test bench for Register file
`timescale 1ns/10ps
`include "regfile.v"

module regstim(); 		

	parameter ClockDelay = 5000;

	reg	[4:0] 	ReadRegister1, ReadRegister2, WriteRegister;
	reg [63:0]	WriteData;
	reg 			RegWrite, clk;
	wire [63:0]	ReadData1, ReadData2;

	integer i;

	// Your register file MUST be named "regfile".
	// Also you must make sure that the port declarations
	// match up with the module instance in this stimulus file.
	regfile dut (.data(WriteData), .DRA(ReadData1), .DRB(ReadData2),
						.RA(ReadRegister1), .RB(ReadRegister2), .RW(WriteRegister),
						.en(RegWrite), .clk(clk));

	//gtkwave file for iverilog
	initial begin
		$dumpfile("testResults.vcd");
		$dumpvars(1, dut);
	end

	// Force %t's to print in a nice format.
	initial $timeformat(-9, 2, " ns", 10);

	initial begin // Set up the clock
		clk <= 0;
		forever #(ClockDelay/2) clk <= ~clk;
	end

	initial begin
		// Try to write the value 0xA0 into register 31.
		// Register 31 should always be at the value of 0.
		RegWrite <= 5'd0;
		ReadRegister1 <= 5'd0;
		ReadRegister2 <= 5'd0;
		WriteRegister <= 5'd31;
		WriteData <= 64'h00000000000000A0;
		@(posedge clk);
		
		$display("%t Attempting overwrite of register 31, which should always be 0", $time);
		RegWrite <= 1;
		@(posedge clk);

		// Write a value into each  register.
		$display("%t Writing pattern to all registers.", $time);
		for (i=0; i<31; i=i+1) begin
			RegWrite <= 0;
			ReadRegister1 <= i-1;
			ReadRegister2 <= i;
			WriteRegister <= i;
			WriteData <= i*64'h0000010204080001;
			@(posedge clk);
			
			RegWrite <= 1;
			@(posedge clk);
		end

		// Go back and verify that the registers
		// retained the data.
		$display("%t Checking pattern.", $time);
		for (i=0; i<32; i=i+1) begin
			RegWrite <= 0;
			ReadRegister1 <= i-1;
			ReadRegister2 <= i;
			WriteRegister <= i;
			WriteData <= i*64'h0000000000000100+i;
			@(posedge clk);
		end
		$stop;
	end
endmodule

lab1/testResults.vcd
$date
	Wed Jan 17 22:39:22 2018
$end
$version
	ModelSim Version 10.1e
$end
$timescale
	1ps
$end
$scope module regstim $end
$scope module dut $end
$var wire 1 ! DRA [63] $end
$var wire 1 " DRA [62] $end
$var wire 1 # DRA [61] $end
$var wire 1 $ DRA [60] $end
$var wire 1 % DRA [59] $end
$var wire 1 & DRA [58] $end
$var wire 1 ' DRA [57] $end
$var wire 1 ( DRA [56] $end
$var wire 1 ) DRA [55] $end
$var wire 1 * DRA [54] $end
$var wire 1 + DRA [53] $end
$var wire 1 , DRA [52] $end
$var wire 1 - DRA [51] $end
$var wire 1 . DRA [50] $end
$var wire 1 / DRA [49] $end
$var wire 1 0 DRA [48] $end
$var wire 1 1 DRA [47] $end
$var wire 1 2 DRA [46] $end
$var wire 1 3 DRA [45] $end
$var wire 1 4 DRA [44] $end
$var wire 1 5 DRA [43] $end
$var wire 1 6 DRA [42] $end
$var wire 1 7 DRA [41] $end
$var wire 1 8 DRA [40] $end
$var wire 1 9 DRA [39] $end
$var wire 1 : DRA [38] $end
$var wire 1 ; DRA [37] $end
$var wire 1 < DRA [36] $end
$var wire 1 = DRA [35] $end
$var wire 1 > DRA [34] $end
$var wire 1 ? DRA [33] $end
$var wire 1 @ DRA [32] $end
$var wire 1 A DRA [31] $end
$var wire 1 B DRA [30] $end
$var wire 1 C DRA [29] $end
$var wire 1 D DRA [28] $end
$var wire 1 E DRA [27] $end
$var wire 1 F DRA [26] $end
$var wire 1 G DRA [25] $end
$var wire 1 H DRA [24] $end
$var wire 1 I DRA [23] $end
$var wire 1 J DRA [22] $end
$var wire 1 K DRA [21] $end
$var wire 1 L DRA [20] $end
$var wire 1 M DRA [19] $end
$var wire 1 N DRA [18] $end
$var wire 1 O DRA [17] $end
$var wire 1 P DRA [16] $end
$var wire 1 Q DRA [15] $end
$var wire 1 R DRA [14] $end
$var wire 1 S DRA [13] $end
$var wire 1 T DRA [12] $end
$var wire 1 U DRA [11] $end
$var wire 1 V DRA [10] $end
$var wire 1 W DRA [9] $end
$var wire 1 X DRA [8] $end
$var wire 1 Y DRA [7] $end
$var wire 1 Z DRA [6] $end
$var wire 1 [ DRA [5] $end
$var wire 1 \ DRA [4] $end
$var wire 1 ] DRA [3] $end
$var wire 1 ^ DRA [2] $end
$var wire 1 _ DRA [1] $end
$var wire 1 ` DRA [0] $end
$var wire 1 a DRB [63] $end
$var wire 1 b DRB [62] $end
$var wire 1 c DRB [61] $end
$var wire 1 d DRB [60] $end
$var wire 1 e DRB [59] $end
$var wire 1 f DRB [58] $end
$var wire 1 g DRB [57] $end
$var wire 1 h DRB [56] $end
$var wire 1 i DRB [55] $end
$var wire 1 j DRB [54] $end
$var wire 1 k DRB [53] $end
$var wire 1 l DRB [52] $end
$var wire 1 m DRB [51] $end
$var wire 1 n DRB [50] $end
$var wire 1 o DRB [49] $end
$var wire 1 p DRB [48] $end
$var wire 1 q DRB [47] $end
$var wire 1 r DRB [46] $end
$var wire 1 s DRB [45] $end
$var wire 1 t DRB [44] $end
$var wire 1 u DRB [43] $end
$var wire 1 v DRB [42] $end
$var wire 1 w DRB [41] $end
$var wire 1 x DRB [40] $end
$var wire 1 y DRB [39] $end
$var wire 1 z DRB [38] $end
$var wire 1 { DRB [37] $end
$var wire 1 | DRB [36] $end
$var wire 1 } DRB [35] $end
$var wire 1 ~ DRB [34] $end
$var wire 1 !! DRB [33] $end
$var wire 1 "! DRB [32] $end
$var wire 1 #! DRB [31] $end
$var wire 1 $! DRB [30] $end
$var wire 1 %! DRB [29] $end
$var wire 1 &! DRB [28] $end
$var wire 1 '! DRB [27] $end
$var wire 1 (! DRB [26] $end
$var wire 1 )! DRB [25] $end
$var wire 1 *! DRB [24] $end
$var wire 1 +! DRB [23] $end
$var wire 1 ,! DRB [22] $end
$var wire 1 -! DRB [21] $end
$var wire 1 .! DRB [20] $end
$var wire 1 /! DRB [19] $end
$var wire 1 0! DRB [18] $end
$var wire 1 1! DRB [17] $end
$var wire 1 2! DRB [16] $end
$var wire 1 3! DRB [15] $end
$var wire 1 4! DRB [14] $end
$var wire 1 5! DRB [13] $end
$var wire 1 6! DRB [12] $end
$var wire 1 7! DRB [11] $end
$var wire 1 8! DRB [10] $end
$var wire 1 9! DRB [9] $end
$var wire 1 :! DRB [8] $end
$var wire 1 ;! DRB [7] $end
$var wire 1 <! DRB [6] $end
$var wire 1 =! DRB [5] $end
$var wire 1 >! DRB [4] $end
$var wire 1 ?! DRB [3] $end
$var wire 1 @! DRB [2] $end
$var wire 1 A! DRB [1] $end
$var wire 1 B! DRB [0] $end
$var wire 1 C! data [63] $end
$var wire 1 D! data [62] $end
$var wire 1 E! data [61] $end
$var wire 1 F! data [60] $end
$var wire 1 G! data [59] $end
$var wire 1 H! data [58] $end
$var wire 1 I! data [57] $end
$var wire 1 J! data [56] $end
$var wire 1 K! data [55] $end
$var wire 1 L! data [54] $end
$var wire 1 M! data [53] $end
$var wire 1 N! data [52] $end
$var wire 1 O! data [51] $end
$var wire 1 P! data [50] $end
$var wire 1 Q! data [49] $end
$var wire 1 R! data [48] $end
$var wire 1 S! data [47] $end
$var wire 1 T! data [46] $end
$var wire 1 U! data [45] $end
$var wire 1 V! data [44] $end
$var wire 1 W! data [43] $end
$var wire 1 X! data [42] $end
$var wire 1 Y! data [41] $end
$var wire 1 Z! data [40] $end
$var wire 1 [! data [39] $end
$var wire 1 \! data [38] $end
$var wire 1 ]! data [37] $end
$var wire 1 ^! data [36] $end
$var wire 1 _! data [35] $end
$var wire 1 `! data [34] $end
$var wire 1 a! data [33] $end
$var wire 1 b! data [32] $end
$var wire 1 c! data [31] $end
$var wire 1 d! data [30] $end
$var wire 1 e! data [29] $end
$var wire 1 f! data [28] $end
$var wire 1 g! data [27] $end
$var wire 1 h! data [26] $end
$var wire 1 i! data [25] $end
$var wire 1 j! data [24] $end
$var wire 1 k! data [23] $end
$var wire 1 l! data [22] $end
$var wire 1 m! data [21] $end
$var wire 1 n! data [20] $end
$var wire 1 o! data [19] $end
$var wire 1 p! data [18] $end
$var wire 1 q! data [17] $end
$var wire 1 r! data [16] $end
$var wire 1 s! data [15] $end
$var wire 1 t! data [14] $end
$var wire 1 u! data [13] $end
$var wire 1 v! data [12] $end
$var wire 1 w! data [11] $end
$var wire 1 x! data [10] $end
$var wire 1 y! data [9] $end
$var wire 1 z! data [8] $end
$var wire 1 {! data [7] $end
$var wire 1 |! data [6] $end
$var wire 1 }! data [5] $end
$var wire 1 ~! data [4] $end
$var wire 1 !" data [3] $end
$var wire 1 "" data [2] $end
$var wire 1 #" data [1] $end
$var wire 1 $" data [0] $end
$var wire 1 %" RA [4] $end
$var wire 1 &" RA [3] $end
$var wire 1 '" RA [2] $end
$var wire 1 (" RA [1] $end
$var wire 1 )" RA [0] $end
$var wire 1 *" RB [4] $end
$var wire 1 +" RB [3] $end
$var wire 1 ," RB [2] $end
$var wire 1 -" RB [1] $end
$var wire 1 ." RB [0] $end
$var wire 1 /" RW [4] $end
$var wire 1 0" RW [3] $end
$var wire 1 1" RW [2] $end
$var wire 1 2" RW [1] $end
$var wire 1 3" RW [0] $end
$var wire 1 4" en $end
$var wire 1 5" clk $end
$var wire 1 6" dec [31] $end
$var wire 1 7" dec [30] $end
$var wire 1 8" dec [29] $end
$var wire 1 9" dec [28] $end
$var wire 1 :" dec [27] $end
$var wire 1 ;" dec [26] $end
$var wire 1 <" dec [25] $end
$var wire 1 =" dec [24] $end
$var wire 1 >" dec [23] $end
$var wire 1 ?" dec [22] $end
$var wire 1 @" dec [21] $end
$var wire 1 A" dec [20] $end
$var wire 1 B" dec [19] $end
$var wire 1 C" dec [18] $end
$var wire 1 D" dec [17] $end
$var wire 1 E" dec [16] $end
$var wire 1 F" dec [15] $end
$var wire 1 G" dec [14] $end
$var wire 1 H" dec [13] $end
$var wire 1 I" dec [12] $end
$var wire 1 J" dec [11] $end
$var wire 1 K" dec [10] $end
$var wire 1 L" dec [9] $end
$var wire 1 M" dec [8] $end
$var wire 1 N" dec [7] $end
$var wire 1 O" dec [6] $end
$var wire 1 P" dec [5] $end
$var wire 1 Q" dec [4] $end
$var wire 1 R" dec [3] $end
$var wire 1 S" dec [2] $end
$var wire 1 T" dec [1] $end
$var wire 1 U" dec [0] $end
$var wire 1 V" outwr $end
$scope begin toplevel[30] $end
$var parameter 32 W" i $end
$upscope $end
$scope begin toplevel[29] $end
$var parameter 32 X" i $end
$upscope $end
$scope begin toplevel[28] $end
$var parameter 32 Y" i $end
$upscope $end
$scope begin toplevel[27] $end
$var parameter 32 Z" i $end
$upscope $end
$scope begin toplevel[26] $end
$var parameter 32 [" i $end
$upscope $end
$scope begin toplevel[25] $end
$var parameter 32 \" i $end
$upscope $end
$scope begin toplevel[24] $end
$var parameter 32 ]" i $end
$upscope $end
$scope begin toplevel[23] $end
$var parameter 32 ^" i $end
$upscope $end
$scope begin toplevel[22] $end
$var parameter 32 _" i $end
$upscope $end
$scope begin toplevel[21] $end
$var parameter 32 `" i $end
$upscope $end
$scope begin toplevel[20] $end
$var parameter 32 a" i $end
$upscope $end
$scope begin toplevel[19] $end
$var parameter 32 b" i $end
$upscope $end
$scope begin toplevel[18] $end
$var parameter 32 c" i $end
$upscope $end
$scope begin toplevel[17] $end
$var parameter 32 d" i $end
$upscope $end
$scope begin toplevel[16] $end
$var parameter 32 e" i $end
$upscope $end
$scope begin toplevel[15] $end
$var parameter 32 f" i $end
$upscope $end
$scope begin toplevel[14] $end
$var parameter 32 g" i $end
$upscope $end
$scope begin toplevel[13] $end
$var parameter 32 h" i $end
$upscope $end
$scope begin toplevel[12] $end
$var parameter 32 i" i $end
$upscope $end
$scope begin toplevel[11] $end
$var parameter 32 j" i $end
$upscope $end
$scope begin toplevel[10] $end
$var parameter 32 k" i $end
$upscope $end
$scope begin toplevel[9] $end
$var parameter 32 l" i $end
$upscope $end
$scope begin toplevel[8] $end
$var parameter 32 m" i $end
$upscope $end
$scope begin toplevel[7] $end
$var parameter 32 n" i $end
$upscope $end
$scope begin toplevel[6] $end
$var parameter 32 o" i $end
$upscope $end
$scope begin toplevel[5] $end
$var parameter 32 p" i $end
$upscope $end
$scope begin toplevel[4] $end
$var parameter 32 q" i $end
$upscope $end
$scope begin toplevel[3] $end
$var parameter 32 r" i $end
$upscope $end
$scope begin toplevel[2] $end
$var parameter 32 s" i $end
$upscope $end
$scope begin toplevel[1] $end
$var parameter 32 t" i $end
$upscope $end
$scope begin toplevel[0] $end
$var parameter 32 u" i $end
$upscope $end
$upscope $end
$upscope $end
$enddefinitions $end
#0
$dumpvars
b0 u"
b1 t"
b10 s"
b11 r"
b100 q"
b101 p"
b110 o"
b111 n"
b1000 m"
b1001 l"
b1010 k"
b1011 j"
b1100 i"
b1101 h"
b1110 g"
b1111 f"
b10000 e"
b10001 d"
b10010 c"
b10011 b"
b10100 a"
b10101 `"
b10110 _"
b10111 ^"
b11000 ]"
b11001 \"
b11010 ["
b11011 Z"
b11100 Y"
b11101 X"
b11110 W"
x`
x_
x^
x]
x\
x[
xZ
xY
xX
xW
xV
xU
xT
xS
xR
xQ
xP
xO
xN
xM
xL
xK
xJ
xI
xH
xG
xF
xE
xD
xC
xB
xA
x@
x?
x>
x=
x<
x;
x:
x9
x8
x7
x6
x5
x4
x3
x2
x1
x0
x/
x.
x-
x,
x+
x*
x)
x(
x'
x&
x%
x$
x#
x"
x!
xB!
xA!
x@!
x?!
x>!
x=!
x<!
x;!
x:!
x9!
x8!
x7!
x6!
x5!
x4!
x3!
x2!
x1!
x0!
x/!
x.!
x-!
x,!
x+!
x*!
x)!
x(!
x'!
x&!
x%!
x$!
x#!
x"!
x!!
x~
x}
x|
x{
xz
xy
xx
xw
xv
xu
xt
xs
xr
xq
xp
xo
xn
xm
xl
xk
xj
xi
xh
xg
xf
xe
xd
xc
xb
xa
xU"
xT"
xS"
xR"
xQ"
xP"
xO"
xN"
xM"
xL"
xK"
xJ"
xI"
xH"
xG"
xF"
xE"
xD"
xC"
xB"
xA"
x@"
x?"
x>"
x="
x<"
x;"
x:"
x9"
x8"
x7"
x6"
0V"
05"
04"
13"
12"
11"
10"
1/"
0."
0-"
0,"
0+"
0*"
0)"
0("
0'"
0&"
0%"
0$"
0#"
0""
0!"
0~!
1}!
0|!
1{!
0z!
0y!
0x!
0w!
0v!
0u!
0t!
0s!
0r!
0q!
0p!
0o!
0n!
0m!
0l!
0k!
0j!
0i!
0h!
0g!
0f!
0e!
0d!
0c!
0b!
0a!
0`!
0_!
0^!
0]!
0\!
0[!
0Z!
0Y!
0X!
0W!
0V!
0U!
0T!
0S!
0R!
0Q!
0P!
0O!
0N!
0M!
0L!
0K!
0J!
0I!
0H!
0G!
0F!
0E!
0D!
0C!
$end
#100000
0N"
0O"
0P"
0Q"
0R"
0S"
0T"
0U"
0F"
0G"
0H"
0I"
0J"
0K"
0L"
0M"
0>"
0?"
0@"
0A"
0B"
0C"
0D"
0E"
06"
07"
08"
09"
0:"
0;"
0<"
0="
#2500000
15"
14"
#2600000
16"
#5000000
05"
#7500000
15"
04"
0}!
0{!
03"
02"
01"
00"
0/"
1)"
1("
1'"
1&"
1%"
#7550000
06"
#7850000
0!
0"
0#
0$
0%
0&
0'
0(
0)
0*
0+
0,
0-
0.
0/
00
01
02
03
04
05
06
07
08
09
0:
0;
0<
0=
0>
0?
0@
0A
0B
0C
0D
0E
0F
0G
0H
0I
0J
0K
0L
0M
0N
0O
0P
0Q
0R
0S
0T
0U
0V
0W
0X
0Y
0Z
0[
0\
0]
0^
0_
0`
#10000000
05"
#12500000
15"
14"
#12600000
1U"
#15000000
05"
#17500000
15"
04"
1$"
1o!
1h!
1a!
1Z!
13"
1."
0)"
0("
0'"
0&"
0%"
#17550000
1T"
#17600000
0T"
0U"
#17650000
x!
x"
x#
x$
x%
x&
x'
x(
x)
x*
x+
x,
x-
x.
x/
x0
x1
x2
x3
x4
x5
x6
x7
x8
x9
x:
x;
x<
x=
x>
x?
x@
xA
xB
xC
xD
xE
xF
xG
xH
xI
xJ
xK
xL
xM
xN
xO
xP
xQ
xR
xS
xT
xU
xV
xW
xX
xY
xZ
x[
x\
x]
x^
x_
x`
#17700000
0!
0"
0#
0$
0%
0&
0'
0(
0)
0*
0+
0,
0-
0.
0/
00
01
02
03
04
05
06
07
08
09
0:
0;
0<
0=
0>
0?
0@
0A
0B
0C
0D
0E
0F
0G
0H
0I
0J
0K
0L
0M
0N
0O
0P
0Q
0R
0S
0T
0U
0V
0W
0X
0Y
0Z
0[
0\
0]
0^
0_
0`
#17750000
x!
x"
x#
x$
x%
x&
x'
x(
x)
x*
x+
x,
x-
x.
x/
x0
x1
x2
x3
x4
x5
x6
x7
x8
x9
x:
x;
x<
x=
x>
x?
x@
xA
xB
xC
xD
xE
xF
xG
xH
xI
xJ
xK
xL
xM
xN
xO
xP
xQ
xR
xS
xT
xU
xV
xW
xX
xY
xZ
x[
x\
x]
x^
x_
x`
#17800000
0!
0"
0#
0$
0%
0&
0'
0(
0)
0*
0+
0,
0-
0.
0/
00
01
02
03
04
05
06
07
08
09
0:
0;
0<
0=
0>
0?
0@
0A
0B
0C
0D
0E
0F
0G
0H
0I
0J
0K
0L
0M
0N
0O
0P
0Q
0R
0S
0T
0U
0V
0W
0X
0Y
0Z
0[
0\
0]
0^
0_
0`
#20000000
05"
#22500000
15"
14"
#22600000
1T"
#25000000
05"
#27500000
15"
04"
0$"
1#"
0o!
1n!
0h!
1g!
0a!
1`!
0Z!
1Y!
03"
12"
0."
1-"
1)"
#27550000
0T"
#27800000
0a
0b
0c
0d
0e
0f
0g
0h
0i
0j
0k
0l
0m
0n
0o
0p
0q
0r
0s
0t
0u
0v
0w
0x
0y
0z
0{
0|
0}
0~
0!!
0"!
0#!
0$!
0%!
0&!
0'!
0(!
0)!
0*!
0+!
0,!
0-!
0.!
0/!
00!
01!
02!
03!
04!
05!
06!
07!
08!
09!
0:!
0;!
0<!
0=!
0>!
0?!
0@!
0A!
0B!
18
1?
1F
1M
1`
#27850000
xa
xb
xc
xd
xe
xf
xg
xh
xi
xj
xk
xl
xm
xn
xo
xp
xq
xr
xs
xt
xu
xv
xw
xx
xy
xz
x{
x|
x}
x~
x!!
x"!
x#!
x$!
x%!
x&!
x'!
x(!
x)!
x*!
x+!
x,!
x-!
x.!
x/!
x0!
x1!
x2!
x3!
x4!
x5!
x6!
x7!
x8!
x9!
x:!
x;!
x<!
x=!
x>!
x?!
x@!
xA!
xB!
#30000000
05"
#32500000
15"
14"
#32600000
1S"
#35000000
05"
#37500000
15"
04"
1$"
1o!
1h!
1a!
1Z!
13"
1."
0)"
1("
#37550000
1R"
#37600000
0R"
0S"
#37800000
1w
1~
1'!
1.!
1A!
08
0?
0F
0M
0`
#37850000
xw
x~
x'!
x.!
xA!
17
1>
1E
1L
1_
#40000000
05"
#42500000
15"
14"
#42600000
1R"
#45000000
05"
#47500000
15"
04"
0$"
0#"
1""
0o!
0n!
1m!
0h!
0g!
1f!
0a!
0`!
1_!
0Z!
0Y!
1X!
03"
02"
11"
0."
0-"
1,"
1)"
#47550000
0R"
#47800000
0a
0b
0c
0d
0e
0f
0g
0h
0i
0j
0k
0l
0m
0n
0o
0p
0q
0r
0s
0t
0u
0v
0w
0x
0y
0z
0{
0|
0}
0~
0!!
0"!
0#!
0$!
0%!
0&!
0'!
0(!
0)!
0*!
0+!
0,!
0-!
0.!
0/!
00!
01!
02!
03!
04!
05!
06!
07!
08!
09!
0:!
0;!
0<!
0=!
0>!
0?!
0@!
0A!
0B!
18
1?
1F
1M
1`
#47850000
xa
xb
xc
xd
xe
xf
xg
xh
xi
xj
xk
xl
xm
xn
xo
xp
xq
xr
xs
xt
xu
xv
xw
xx
xy
xz
x{
x|
x}
x~
x!!
x"!
x#!
x$!
x%!
x&!
x'!
x(!
x)!
x*!
x+!
x,!
x-!
x.!
x/!
x0!
x1!
x2!
x3!
x4!
x5!
x6!
x7!
x8!
x9!
x:!
x;!
x<!
x=!
x>!
x?!
x@!
xA!
xB!
#50000000
05"
#52500000
15"
14"
#52600000
1Q"
#55000000
05"
#57500000
15"
04"
1$"
1o!
1h!
1a!
1Z!
13"
1."
0)"
0("
1'"
#57550000
1P"
#57600000
0P"
0Q"
#57700000
x!
x"
x#
x$
x%
x&
x'
x(
x)
x*
x+
x,
x-
x.
x/
x0
x1
x2
x3
x4
x5
x6
x9
x:
x;
x<
x=
x@
xA
xB
xC
xD
xG
xH
xI
xJ
xK
xN
xO
xP
xQ
xR
xS
xT
xU
xV
xW
xX
xY
xZ
x[
x\
x]
x^
#57750000
x7
x8
x>
x?
xE
xF
xL
xM
x_
x`
#57800000
1v
1}
1&!
1-!
1@!
0!
0"
0#
0$
0%
0&
0'
0(
0)
0*
0+
0,
0-
0.
0/
00
01
02
03
04
05
06
07
08
09
0:
0;
0<
0=
0>
0?
0@
0A
0B
0C
0D
0E
0F
0G
0H
0I
0J
0K
0L
0M
0N
0O
0P
0Q
0R
0S
0T
0U
0V
0W
0X
0Y
0Z
0[
0\
0]
0^
0_
0`
#57850000
xv
x}
x&!
x-!
x@!
16
1=
1D
1K
1^
#60000000
05"
#62500000
15"
14"
#62600000
1P"
#65000000
05"
#67500000
15"
04"
0$"
1#"
0o!
1n!
0h!
1g!
0a!
1`!
0Z!
1Y!
03"
12"
0."
1-"
1)"
#67550000
0P"
#67800000
0a
0b
0c
0d
0e
0f
0g
0h
0i
0j
0k
0l
0m
0n
0o
0p
0q
0r
0s
0t
0u
0v
0w
0x
0y
0z
0{
0|
0}
0~
0!!
0"!
0#!
0$!
0%!
0&!
0'!
0(!
0)!
0*!
0+!
0,!
0-!
0.!
0/!
00!
01!
02!
03!
04!
05!
06!
07!
08!
09!
0:!
0;!
0<!
0=!
0>!
0?!
0@!
0A!
0B!
18
1?
1F
1M
1`
#67850000
xa
xb
xc
xd
xe
xf
xg
xh
xi
xj
xk
xl
xm
xn
xo
xp
xq
xr
xs
xt
xu
xv
xw
xx
xy
xz
x{
x|
x}
x~
x!!
x"!
x#!
x$!
x%!
x&!
x'!
x(!
x)!
x*!
x+!
x,!
x-!
x.!
x/!
x0!
x1!
x2!
x3!
x4!
x5!
x6!
x7!
x8!
x9!
x:!
x;!
x<!
x=!
x>!
x?!
x@!
xA!
xB!
#70000000
05"
#72500000
15"
14"
#72600000
1O"
#75000000
05"
#77500000
15"
04"
1$"
1o!
1h!
1a!
1Z!
13"
1."
0)"
1("
#77550000
1N"
#77600000
0N"
0O"
#77800000
1v
1w
1}
1~
1&!
1'!
1-!
1.!
1@!
1A!
06
08
0=
0?
0D
0F
0K
0M
0^
0`
#77850000
xv
xw
x}
x~
x&!
x'!
x-!
x.!
x@!
xA!
16
17
1=
1>
1D
1E
1K
1L
1^
1_
#80000000
05"
#82500000
15"
14"
#82600000
1N"
#85000000
05"
#87500000
15"
04"
0$"
0#"
0""
1!"
0o!
0n!
0m!
1l!
0h!
0g!
0f!
1e!
0a!
0`!
0_!
1^!
0Z!
0Y!
0X!
1W!
03"
02"
01"
10"
0."
0-"
0,"
1+"
1)"
#87550000
0N"
#87700000
0a
0b
0c
0d
0e
0f
0g
0h
0i
0j
0k
0l
0m
0n
0o
0p
0q
0r
0s
0t
0u
0v
0w
0x
0y
0z
0{
0|
0}
0~
0!!
0"!
0#!
0$!
0%!
0&!
0'!
0(!
0)!
0*!
0+!
0,!
0-!
0.!
0/!
00!
01!
02!
03!
04!
05!
06!
07!
08!
09!
0:!
0;!
0<!
0=!
0>!
0?!
0@!
0A!
0B!
#87750000
xa
xb
xc
xd
xe
xf
xg
xh
xi
xj
xk
xl
xm
xn
xo
xp
xq
xr
xs
xt
xu
xv
xw
xx
xy
xz
x{
x|
x}
x~
x!!
x"!
x#!
x$!
x%!
x&!
x'!
x(!
x)!
x*!
x+!
x,!
x-!
x.!
x/!
x0!
x1!
x2!
x3!
x4!
x5!
x6!
x7!
x8!
x9!
x:!
x;!
x<!
x=!
x>!
x?!
x@!
xA!
xB!
#87800000
0a
0b
0c
0d
0e
0f
0g
0h
0i
0j
0k
0l
0m
0n
0o
0p
0q
0r
0s
0t
0u
0v
0w
0x
0y
0z
0{
0|
0}
0~
0!!
0"!
0#!
0$!
0%!
0&!
0'!
0(!
0)!
0*!
0+!
0,!
0-!
0.!
0/!
00!
01!
02!
03!
04!
05!
06!
07!
08!
09!
0:!
0;!
0<!
0=!
0>!
0?!
0@!
0A!
0B!
18
1?
1F
1M
1`
#87850000
xa
xb
xc
xd
xe
xf
xg
xh
xi
xj
xk
xl
xm
xn
xo
xp
xq
xr
xs
xt
xu
xv
xw
xx
xy
xz
x{
x|
x}
x~
x!!
x"!
x#!
x$!
x%!
x&!
x'!
x(!
x)!
x*!
x+!
x,!
x-!
x.!
x/!
x0!
x1!
x2!
x3!
x4!
x5!
x6!
x7!
x8!
x9!
x:!
x;!
x<!
x=!
x>!
x?!
x@!
xA!
xB!
#90000000
05"
#92500000
15"
14"
#92600000
1M"
#95000000
05"
#97500000
15"
04"
1$"
1o!
1h!
1a!
1Z!
13"
1."
0)"
0("
0'"
1&"
#97550000
1L"
#97600000
0L"
0M"
#97700000
06
07
08
0=
0>
0?
0D
0E
0F
0K
0L
0M
0^
0_
0`
#97750000
x!
x"
x#
x$
x%
x&
x'
x(
x)
x*
x+
x,
x-
x.
x/
x0
x1
x2
x3
x4
x5
x6
x7
x8
x9
x:
x;
x<
x=
x>
x?
x@
xA
xB
xC
xD
xE
xF
xG
xH
xI
xJ
xK
xL
xM
xN
xO
xP
xQ
xR
xS
xT
xU
xV
xW
xX
xY
xZ
x[
x\
x]
x^
x_
x`
#97800000
1u
1|
1%!
1,!
1?!
0!
0"
0#
0$
0%
0&
0'
0(
0)
0*
0+
0,
0-
0.
0/
00
01
02
03
04
05
06
07
08
09
0:
0;
0<
0=
0>
0?
0@
0A
0B
0C
0D
0E
0F
0G
0H
0I
0J
0K
0L
0M
0N
0O
0P
0Q
0R
0S
0T
0U
0V
0W
0X
0Y
0Z
0[
0\
0]
0^
0_
0`
#97850000
xu
x|
x%!
x,!
x?!
15
1<
1C
1J
1]
#100000000
05"
#102500000
15"
14"
#102600000
1L"
#105000000
05"
#107500000
15"
04"
0$"
1#"
0o!
1n!
0h!
1g!
0a!
1`!
0Z!
1Y!
03"
12"
0."
1-"
1)"
#107550000
0L"
#107800000
0a
0b
0c
0d
0e
0f
0g
0h
0i
0j
0k
0l
0m
0n
0o
0p
0q
0r
0s
0t
0u
0v
0w
0x
0y
0z
0{
0|
0}
0~
0!!
0"!
0#!
0$!
0%!
0&!
0'!
0(!
0)!
0*!
0+!
0,!
0-!
0.!
0/!
00!
01!
02!
03!
04!
05!
06!
07!
08!
09!
0:!
0;!
0<!
0=!
0>!
0?!
0@!
0A!
0B!
18
1?
1F
1M
1`
