lab1/multiplex.v
module multiplex (in, out, read, clk, reset);
	output [63:0] out;

	input [4:0] read;
	input clk, reset;
	input [31:0][63:0] in;

	assign out = in[read];

endmodule

lab1/D_FF.v
module D_FF (q, d, reset, clk);
  output reg q;
  input d, reset, clk;

  always @(posedge clk)
  if (reset)
    q <= 0;  // On reset, set to 0
  else
    q <= d; // Otherwise out = d
endmodule

lab1/register.v
`include "D_FF.v"

module register (in, out, en, clk);
	output [63:0] out;

	input [63:0] in;
	input en, clk;

	generate
		genvar i; 
		for (i = 0; i < 64; i = i + 1'b1) begin
			D_FF set (.q(out[i]), .d(in[i]), .reset(~en), .clk(clk));
		end
	endgenerate

endmodule

lab1/decoder.v
module decoder (in, out, en);
	output wire [31:0] out;

	input en;
	input [4:0] in;

	wire [3:0] dec;

	decoder2to4 first (.in(in[4:3]), .out(dec), .en(en));

	decoder3to8 second (.in(in[2:0]), .out(out[7:0]), .en(dec[0]));
	decoder3to8 third (.in(in[2:0]), .out(out[15:8]), .en(dec[1]));
	decoder3to8 fourth (.in(in[2:0]), .out(out[23:16]), .en(dec[2]));
	decoder3to8 fifth (.in(in[2:0]), .out(out[31:24]), .en(dec[3]));
		
endmodule

module decoder3to8 (in, out, en);
	output wire [7:0] out;

	input en;
	input [2:0] in;

	assign out[0] = ~in[0] & ~in[1] & ~in[2] & en;
	assign out[1] = in[0] & ~in[1] & ~in[2] & en;
	assign out[2] = ~in[0] & in[1] & ~in[2] & en;
	assign out[3] = in[0] & in[1] & ~in[2] & en;
	assign out[4] = ~in[0] & ~in[1] & in[2] & en;
	assign out[5] = in[0] & ~in[1] & in[2] & en;
	assign out[6] = ~in[0] & in[1] & in[2] & en;
	assign out[7] = in[0] & in[1] & in[2] & en;
endmodule


module decoder2to4 (in, out, en);
	output wire [3:0] out;

	input en;
	input [1:0] in;

	assign out[3] = in[0] & in[1] & en;
	assign out[2] = ~in[0] & in[1] & en;
	assign out[1] = in[0] & ~in[1] & en;
	assign out[0] = ~in[0] & ~in[1] & en;
endmodule

lab1/regfile.v
`include "multiplex.v"
`include "decoder.v"
`include "register.v"

module regfile (data, DRA, DRB, RA, RB, RW, en, clk);
	
	output [63:0] DRA, DRB;
	input [63:0] data;
	input [4:0] RA, RB, RW;
	input en, clk;

	wire [31:0] dec;
	wire [31:0][63:0] outwr;

	decoder start (.in(RW), .out(dec), .en(en));
	assign dec[31] = 1'b0;

	generate
		genvar i;
		for (i = 0; i < 31; i = i + 1'b1) begin
			register set (.in(data), .out(outwr[i]), .en(dec[i]), .clk(clk));
		end
	endgenerate

	multiplex one (.in(outwr), .out(DRA), .read(RA), .clk(clk), .reset(reset));
	multiplex two (.in(outwr), .out(DRB), .read(RB), .clk(clk), .reset(reset));

endmodule

lab1/regstim.v
// Test bench for Register file
`timescale 1ns/10ps
`include "regfile.v"

module regstim(); 		

	parameter ClockDelay = 5000;

	reg	[4:0] 	ReadRegister1, ReadRegister2, WriteRegister;
	reg [63:0]	WriteData;
	reg 			RegWrite, clk;
	wire [63:0]	ReadData1, ReadData2;

	integer i;

	// Your register file MUST be named "regfile".
	// Also you must make sure that the port declarations
	// match up with the module instance in this stimulus file.
	regfile dut (.data(WriteData), .DRA(ReadData1), .DRB(ReadData2),
						.RA(ReadRegister1), .RB(ReadRegister2), .RW(WriteRegister),
						.en(RegWrite), .clk(clk));

	//gtkwave file for iverilog
	initial begin
		$dumpfile("testResults.vcd");
		$dumpvars(1, dut);
	end

	// Force %t's to print in a nice format.
	initial $timeformat(-9, 2, " ns", 10);

	initial begin // Set up the clock
		clk <= 0;
		forever #(ClockDelay/2) clk <= ~clk;
	end

	initial begin
		// Try to write the value 0xA0 into register 31.
		// Register 31 should always be at the value of 0.
		RegWrite <= 5'd0;
		ReadRegister1 <= 5'd0;
		ReadRegister2 <= 5'd0;
		WriteRegister <= 5'd31;
		WriteData <= 64'h00000000000000A0;
		@(posedge clk);
		
		$display("%t Attempting overwrite of register 31, which should always be 0", $time);
		RegWrite <= 1;
		@(posedge clk);

		// Write a value into each  register.
		$display("%t Writing pattern to all registers.", $time);
		for (i=0; i<31; i=i+1) begin
			RegWrite <= 0;
			ReadRegister1 <= i-1;
			ReadRegister2 <= i;
			WriteRegister <= i;
			WriteData <= i*64'h0000010204080001;
			@(posedge clk);
			
			RegWrite <= 1;
			@(posedge clk);
		end

		// Go back and verify that the registers
		// retained the data.
		$display("%t Checking pattern.", $time);
		for (i=0; i<32; i=i+1) begin
			RegWrite <= 0;
			ReadRegister1 <= i-1;
			ReadRegister2 <= i;
			WriteRegister <= i;
			WriteData <= i*64'h0000000000000100+i;
			@(posedge clk);
		end
		$stop;
	end
endmodule

lab1/testResults.vcd
$date
	Sun Jan 14 15:28:33 2018
$end
$version
	Icarus Verilog
$end
$timescale
	10ps
$end
$scope module regstim $end
$scope module dut $end
$var wire 5 ! RA [4:0] $end
$var wire 5 " RB [4:0] $end
$var wire 5 # RW [4:0] $end
$var wire 1 $ clk $end
$var wire 64 % data [63:0] $end
$var wire 1 & en $end
$var wire 1 ' reset $end
$var wire 2048 ( outwr [2047:0] $end
$var wire 32 ) dec [31:0] $end
$var wire 64 * DRB [63:0] $end
$var wire 64 + DRA [63:0] $end
$upscope $end
$upscope $end
$enddefinitions $end
#0
$dumpvars
bx +
bx *
b10000000000000000000000000000000 )
b0xxxxxxxxxxxxxxxxxxxxxxxxxxxxxxxxxxxxxxxxxxxxxxxxxxxxxxxxxxxxxxxxxxxxxxxxxxxxxxxxxxxxxxxxxxxxxxxxxxxxxxxxxxxxxxxxxxxxxxxxxxxxxxxxxxxxxxxxxxxxxxxxxxxxxxxxxxxxxxxxxxxxxxxxxxxxxxxxxxxxxxxxxxxxxxxxxxxxxxxxxxxxxxxxxxxxxxxxxxxxxxxxxxxxxxxxxxxxxxxxxxxxxxxxxxxxxxxxxxxxxxxxxxxxxxxxxxxxxxxxxxxxxxxxxxxxxxxxxxxxxxxxxxxxxxxxxxxxxxxxxxxxxxxxxxxxxxxxxxxxxxxxxxxxxxxxxxxxxxxxxxxxxxxxxxxxxxxxxxxxxxxxxxxxxxxxxxxxxxxxxxxxxxxxxxxxxxxxxxxxxxxxxxxxxxxxxxxxxxxxxxxxxxxxxxxxxxxxxxxxxxxxxxxxxxxxxxxxxxxxxxxxxxxxxxxxxxxxxxxxxxxxxxxxxxxxxxxxxxxxxxxxxxxxxxxxxxxxxxxxxxxxxxxxxxxxxxxxxxxxxxxxxxxxxxxxxxxxxxxxxxxxxxxxxxxxxxxxxxxxxxxxxxxxxxxxxxxxxxxxxxxxxxxxxxxxxxxxxxxxxxxxxxxxxxxxxxxxxxxxxxxxxxxxxxxxxxxxxxxxxxxxxxxxxxxxxxxxxxxxxxxxxxxxxxxxxxxxxxxxxxxxxxxxxxxxxxxxxxxxxxxxxxxxxxxxxxxxxxxxxxxxxxxxxxxxxxxxxxxxxxxxxxxxxxxxxxxxxxxxxxxxxxxxxxxxxxxxxxxxxxxxxxxxxxxxxxxxxxxxxxxxxxxxxxxxxxxxxxxxxxxxxxxxxxxxxxxxxxxxxxxxxxxxxxxxxxxxxxxxxxxxxxxxxxxxxxxxxxxxxxxxxxxxxxxxxxxxxxxxxxxxxxxxxxxxxxxxxxxxxxxxxxxxxxxxxxxxxxxxxxxxxxxxxxxxxxxxxxxxxxxxxxxxxxxxxxxxxxxxxxxxxxxxxxxxxxxxxxxxxxxxxxxxxxxxxxxxxxxxxxxxxxxxxxxxxxxxxxxxxxxxxxxxxxxxxxxxxxxxxxxxxxxxxxxxxxxxxxxxxxxxxxxxxxxxxxxxxxxxxxxxxxxxxxxxxxxxxxxxxxxxxxxxxxxxxxxxxxxxxxxxxxxxxxxxxxxxxxxxxxxxxxxxxxxxxxxxxxxxxxxxxxxxxxxxxxxxxxxxxxxxxxxxxxxxxxxxxxxxxxxxxxxxxxxxxxxxxxxxxxxxxxxxxxxxxxxxxxxxxxxxxxxxxxxxxxxxxxxxxxxxxxxxxxxxxxxxxxxxxxxxxxxxxxxxxxxxxxxxxxxxxxxxxxxxxxxxxxxxxxxxxxxxxxxxxxxxxxxxxxxxxxxxxxxxxxxxxxxxxxxxxxxxxxxxxxxxxxxxxxxxxxxxxxxxxxxxxxxxxxxxxxxxxxxxxxxxxxxxxxxxxxxxxxxxxxxxxxxxxxxxxxxxxxxxxxxxxxxxxxxxxxxxxxxxxxxxxxxxxxxxxxxxxxxxxxxxxxxxxxxxxxxxxxxxxxxxxxxxxxxxxxxxxxxxxxxxxxxxxxxxxxxxxxxxxxxxxxxxxxxxxxxxxxxxxxxxxxxxxxxxxxxxxxxxxxxxxxxxxxxxxxxxxxxxxxxxxxxxxxxxxxxxxxxxxxxxxxxxxxxxxxxxxxxxxxxxxxxxxxxxxxxxxxxxxxxxxxxxxxxxxxxxxxxxxxxxxxxxxxxxxxxxxxxxxxxxxxxxxxxxxxxxxxxxxxxxxxxxxxxxxxxxxxxxxxxxxxxxxxxxxxxxxxxxxxxxxxxxxxxxxxxxxxxxxxxxxxxxxxxxxxxxxxxxxxxxxxxxxxxxxxxxxxxxxxxxxxxxxxxxxxxxxxxxxxxxxxxxxxxxxxxxxxxxxxxxxxxxxxxxxxxxxxxxxxxxxxxxxxxxxxxxxxxxxxxxxxxxxxxx (
z'
0&
b10100000 %
0$
b11111 #
b0 "
b0 !
$end
#250000
b0 +
b0 *
b0 (
1&
1$
#500000
0$
#750000
b1 )
b0 %
b0 #
b11111 !
0&
1$
#1000000
0$
#1250000
1&
1$
#1500000
0$
#1750000
b10000 )
b10000001000000100000010000000000000000001 %
b1 #
b1 "
b0 !
0&
1$
#2000000
0$
#2250000
b100000010000001000000100000000000000000010000000000000000000000000000000000000000000000000000000000000000000000000000000000000000000000000000000000000000000000000000000000000000000000000000000000000000000000000000000000000000000000000000000000000000000000000000000000000000000000000000000000000000 (
1&
1$
#2500000
0$
#2750000
b100 )
b100000010000001000000100000000000000000010 %
b10 #
b10 "
b1 !
0&
1$
#3000000
0$
#3250000
b100000010000001000000100000000000000000010 *
b10000001000000100000010000000000000000001000000000000000000000000000000000000000000000000000000000000000000000000000000000000000000000000000000000000000000000000000000000 (
1&
1$
#3500000
0$
#3750000
b1000000 )
b110000011000001100000110000000000000000011 %
b11 #
b0 *
b11 "
b100000010000001000000100000000000000000010 +
b10 !
0&
1$
#4000000
0$
#4250000
b0 +
b110000011000001100000110000000000000000011000000000000000000000000000000000000000000000000000000000000000000000000000000000000000000000000000000000000000000000000000000000000000000000000000000000000000000000000000000000000000000000000000000000000000000000000000000000000000000000000000000000000000000000000000000000000000000000000000000000000000000000000000000000000000000000000000000000000000000000000000000000000000000000000 (
1&
1$
#4500000
0$
#4750000
b10 )
b1000000100000010000001000000000000000000100 %
b100 #
b100 "
b11 !
0&
1$
#5000000
0$
#5250000
b10000001000000100000010000000000000000001000000000000000000000000000000000000000000000000000000000000000000 (
1&
1$
#5500000
0$
#5750000
b100000 )
b1010000101000010100001010000000000000000101 %
b101 #
b101 "
b100 !
0&
1$
#6000000
0$
#6250000
b1010000101000010100001010000000000000000101 *
b101000010100001010000101000000000000000010100000000000000000000000000000000000000000000000000000000000000000000000000000000000000000000000000000000000000000000000000000000000000000000000000000000000000000000000000000000000000000000000000000000000000000000000000000000000000000000000000000000000000000000000000000000000000000000000000000000000000000000000000000000 (
1&
1$
#6500000
0$
#6750000
b1000 )
b1100000110000011000001100000000000000000110 %
b110 #
b0 *
b110 "
b1010000101000010100001010000000000000000101 +
b101 !
0&
1$
#7000000
0$
#7250000
b0 +
b1100000110000011000001100000000000000000110000000000000000000000000000000000000000000000000000000000000000000000000000000000000000000000000000000000000000000000000000000000000000000000000000000000000000000000000000000000000000000000000 (
1&
1$
#7500000
0$
#7750000
b10000000 )
b1110000111000011100001110000000000000000111 %
b111 #
b111 "
b110 !
0&
1$
#8000000
0$
#8250000
b1110000111000011100001110000000000000000111 *
b11100001110000111000011100000000000000001110000000000000000000000000000000000000000000000000000000000000000000000000000000000000000000000000000000000000000000000000000000000000000000000000000000000000000000000000000000000000000000000000000000000000000000000000000000000000000000000000000000000000000000000000000000000000000000000000000000000000000000000000000000000000000000000000000000000000000000000000000000000000000000000000000000000000000000000000000000000000000000000000000000000000000 (
1&
1$
#8500000
0$
#8750000
b10000000000000000 )
b10000001000000100000010000000000000000001000 %
b1000 #
b0 *
b1000 "
b1110000111000011100001110000000000000000111 +
b111 !
0&
1$
#9000000
0$
#9250000
b0 +
b100000010000001000000100000000000000000010000000000000000000000000000000000000000000000000000000000000000000000000000000000000000000000000000000000000000000000000000000000000000000000000000000000000000000000000000000000000000000000000000000000000000000000000000000000000000000000000000000000000000000000000000000000000000000000000000000000000000000000000000000000000000000000000000000000000000000000000000000000000000000000000000000000000000000000000000000000000000000000000000000000000000000000000000000000000000000000000000000000000000000000000000000000000000000000000000000000000000000000000000000000000000000000000000000000000000000000000000000000000000000000000000000000000000000000000000000000000000000000000000000000000000000000000000000000000000000000000000000000000000000000000000000000000000000000000000000000000000000000000000000000000000000000000000000000000000000000000000000000000000000000000000000000000000000000000000000000000000000000000000000000000000000000000000000000000000000000000000000000000000000000000000000000000000000000000000000000000000000 (
1&
1$
#9500000
0$
#9750000
b100000000000000000000 )
b10010001001000100100010010000000000000001001 %
b1001 #
b1001 "
b1000 !
0&
1$
#10000000
0$
#10250000
b1001000100100010010001001000000000000000100100000000000000000000000000000000000000000000000000000000000000000000000000000000000000000000000000000000000000000000000000000000000000000000000000000000000000000000000000000000000000000000000000000000000000000000000000000000000000000000000000000000000000000000000000000000000000000000000000000000000000000000000000000000000000000000000000000000000000000000000000000000000000000000000000000000000000000000000000000000000000000000000000000000000000000000000000000000000000000000000000000000000000000000000000000000000000000000000000000000000000000000000000000000000000000000000000000000000000000000000000000000000000000000000000000000000000000000000000000000000000000000000000000000000000000000000000000000000000000000000000000000000000000000000000000000000000000000000000000000000000000000000000000000000000000000000000000000000000000000000000000000000000000000000000000000000000000000000000000000000000000000000000000000000000000000000000000000000000000000000000000000000000000000000000000000000000000000000000000000000000000000000000000000000000000000000000000000000000000000000000000000000000000000000000000000000000000000000000000000000000000000000000000000000000000000000000000000000000000000000000000000000000000000000000000000000000000000000000000000000000000000000000000000 (
1&
1$
#10500000
0$
#10750000
b1000000000000000000 )
b10100001010000101000010100000000000000001010 %
b1010 #
b1010 "
b1001 !
0&
1$
#11000000
0$
#11250000
b10100001010000101000010100000000000000001010000000000000000000000000000000000000000000000000000000000000000000000000000000000000000000000000000000000000000000000000000000000000000000000000000000000000000000000000000000000000000000000000000000000000000000000000000000000000000000000000000000000000000000000000000000000000000000000000000000000000000000000000000000000000000000000000000000000000000000000000000000000000000000000000000000000000000000000000000000000000000000000000000000000000000000000000000000000000000000000000000000000000000000000000000000000000000000000000000000000000000000000000000000000000000000000000000000000000000000000000000000000000000000000000000000000000000000000000000000000000000000000000000000000000000000000000000000000000000000000000000000000000000000000000000000000000000000000000000000000000000000000000000000000000000000000000000000000000000000000000000000000000000000000000000000000000000000000000000000000000000000000000000000000000000000000000000000000000000000000000000000000000000000000000000000000000000000000000000000000000000000000000000000000000000000000000000000000000000000000000000000000000000000000000000000000000000000000000000000000000000000000000 (
1&
1$
#11500000
0$
#11750000
b10000000000000000000000 )
b10110001011000101100010110000000000000001011 %
b1011 #
b1011 "
b1010 !
0&
1$
#12000000
0$
#12250000
b101100010110001011000101100000000000000010110000000000000000000000000000000000000000000000000000000000000000000000000000000000000000000000000000000000000000000000000000000000000000000000000000000000000000000000000000000000000000000000000000000000000000000000000000000000000000000000000000000000000000000000000000000000000000000000000000000000000000000000000000000000000000000000000000000000000000000000000000000000000000000000000000000000000000000000000000000000000000000000000000000000000000000000000000000000000000000000000000000000000000000000000000000000000000000000000000000000000000000000000000000000000000000000000000000000000000000000000000000000000000000000000000000000000000000000000000000000000000000000000000000000000000000000000000000000000000000000000000000000000000000000000000000000000000000000000000000000000000000000000000000000000000000000000000000000000000000000000000000000000000000000000000000000000000000000000000000000000000000000000000000000000000000000000000000000000000000000000000000000000000000000000000000000000000000000000000000000000000000000000000000000000000000000000000000000000000000000000000000000000000000000000000000000000000000000000000000000000000000000000000000000000000000000000000000000000000000000000000000000000000000000000000000000000000000000000000000000000000000000000000000000000000000000000000000000000000000000000000000000000000000000000000000000000000000000000000000000000000000000000000000000000000 (
1&
1$
#12500000
0$
#12750000
b100000000000000000 )
b11000001100000110000011000000000000000001100 %
b1100 #
b1100 "
b1011 !
0&
1$
#13000000
0$
#13250000
b1100000110000011000001100000000000000000110000000000000000000000000000000000000000000000000000000000000000000000000000000000000000000000000000000000000000000000000000000000000000000000000000000000000000000000000000000000000000000000000000000000000000000000000000000000000000000000000000000000000000000000000000000000000000000000000000000000000000000000000000000000000000000000000000000000000000000000000000000000000000000000000000000000000000000000000000000000000000000000000000000000000000000000000000000000000000000000000000000000000000000000000000000000000000000000000000000000000000000000000000000000000000000000000000000000000000000000000000000000000000000000000000000000000000000000000000000000000000000000000000000000000000000000000000000000000000000000000000000000000000000000000000000000000000000000000000000000000000000000000000000000000000000000000000000000000000000000000000000000000000000000000000000000000000000000000000000000000000000000000000000000000000000000000000000000000000000000000000000000000000000000000000000000000000000000000000000000000000000000000000000000000000000000000000000000000000000000000000000000 (
1&
1$
#13500000
0$
#13750000
b1000000000000000000000 )
b11010001101000110100011010000000000000001101 %
b1101 #
b1101 "
b1100 !
0&
1$
#14000000
0$
#14250000
b11010001101000110100011010000000000000001101000000000000000000000000000000000000000000000000000000000000000000000000000000000000000000000000000000000000000000000000000000000000000000000000000000000000000000000000000000000000000000000000000000000000000000000000000000000000000000000000000000000000000000000000000000000000000000000000000000000000000000000000000000000000000000000000000000000000000000000000000000000000000000000000000000000000000000000000000000000000000000000000000000000000000000000000000000000000000000000000000000000000000000000000000000000000000000000000000000000000000000000000000000000000000000000000000000000000000000000000000000000000000000000000000000000000000000000000000000000000000000000000000000000000000000000000000000000000000000000000000000000000000000000000000000000000000000000000000000000000000000000000000000000000000000000000000000000000000000000000000000000000000000000000000000000000000000000000000000000000000000000000000000000000000000000000000000000000000000000000000000000000000000000000000000000000000000000000000000000000000000000000000000000000000000000000000000000000000000000000000000000000000000000000000000000000000000000000000000000000000000000000000000000000000000000000000000000000000000000000000000000000000000000000000000000000000000000000000000000000000000000000000000000000000000000000000000000000000000000000000000000000000000000000 (
1&
1$
#14500000
0$
#14750000
b10000000000000000000 )
b11100001110000111000011100000000000000001110 %
b1110 #
b1110 "
b1101 !
0&
1$
#15000000
0$
#15250000
b111000011100001110000111000000000000000011100000000000000000000000000000000000000000000000000000000000000000000000000000000000000000000000000000000000000000000000000000000000000000000000000000000000000000000000000000000000000000000000000000000000000000000000000000000000000000000000000000000000000000000000000000000000000000000000000000000000000000000000000000000000000000000000000000000000000000000000000000000000000000000000000000000000000000000000000000000000000000000000000000000000000000000000000000000000000000000000000000000000000000000000000000000000000000000000000000000000000000000000000000000000000000000000000000000000000000000000000000000000000000000000000000000000000000000000000000000000000000000000000000000000000000000000000000000000000000000000000000000000000000000000000000000000000000000000000000000000000000000000000000000000000000000000000000000000000000000000000000000000000000000000000000000000000000000000000000000000000000000000000000000000000000000000000000000000000000000000000000000000000000000000000000000000000000000000000000000000000000000000000000000000000000000000000000000000000000000000000000000000000000000000000000000000000000000000000000000000000000000000000000000000000000000000000000000000000000000000000000000000000000 (
1&
1$
#15500000
0$
#15750000
b100000000000000000000000 )
b11110001111000111100011110000000000000001111 %
b1111 #
b1111 "
b1110 !
0&
1$
#16000000
0$
#16250000
b1111000111100011110001111000000000000000111100000000000000000000000000000000000000000000000000000000000000000000000000000000000000000000000000000000000000000000000000000000000000000000000000000000000000000000000000000000000000000000000000000000000000000000000000000000000000000000000000000000000000000000000000000000000000000000000000000000000000000000000000000000000000000000000000000000000000000000000000000000000000000000000000000000000000000000000000000000000000000000000000000000000000000000000000000000000000000000000000000000000000000000000000000000000000000000000000000000000000000000000000000000000000000000000000000000000000000000000000000000000000000000000000000000000000000000000000000000000000000000000000000000000000000000000000000000000000000000000000000000000000000000000000000000000000000000000000000000000000000000000000000000000000000000000000000000000000000000000000000000000000000000000000000000000000000000000000000000000000000000000000000000000000000000000000000000000000000000000000000000000000000000000000000000000000000000000000000000000000000000000000000000000000000000000000000000000000000000000000000000000000000000000000000000000000000000000000000000000000000000000000000000000000000000000000000000000000000000000000000000000000000000000000000000000000000000000000000000000000000000000000000000000000000000000000000000000000000000000000000000000000000000000000000000000000000000000000000000000000000000000000000000000000000000000000000000000000000000000000000000000000000000000000000000 (
1&
1$
#16500000
0$
#16750000
b100000000 )
b100000010000001000000100000000000000000010000 %
b10000 #
b10000 "
b1111 !
0&
1$
#17000000
0$
#17250000
b10000001000000100000010000000000000000001000000000000000000000000000000000000000000000000000000000000000000000000000000000000000000000000000000000000000000000000000000000000000000000000000000000000000000000000000000000000000000000000000000000000000000000000000000000000000000000000000000000000000000000000000000000000000000000000000000000000000000000000000000000000000000000000000000000000000000000000000000000000000000000000000000000000000000000000000000000000000000000000000000000000000000000000000000000000000000000000000000000000000000000000000000000000 (
1&
1$
#17500000
0$
#17750000
b1000000000000 )
b100010010001001000100100010000000000000010001 %
b10001 #
b10001 "
b10000 !
0&
1$
#18000000
0$
#18250000
b100010010001001000100100010000000000000010001000000000000000000000000000000000000000000000000000000000000000000000000000000000000000000000000000000000000000000000000000000000000000000000000000000000000000000000000000000000000000000000000000000000000000000000000000000000000000000000000000000000000000000000000000000000000000000000000000000000000000000000000000000000000000000000000000000000000000000000000000000000000000000000000000000000000000000000000000000000000000000000000000000000000000000000000000000000000000000000000000000000000000000000000000000000000000000000000000000000000000000000000000000000000000000000000000000000000000000000000000000000000000000000000000000000000000000000000000000000000000000000000000000000000000000000000000000000000000000000000000000000000000000000000000000000000000000000000 (
1&
1$
#18500000
0$
#18750000
b10000000000 )
b100100010010001001000100100000000000000010010 %
b10010 #
b10010 "
b10001 !
0&
1$
#19000000
0$
#19250000
b1001000100100010010001001000000000000000100100000000000000000000000000000000000000000000000000000000000000000000000000000000000000000000000000000000000000000000000000000000000000000000000000000000000000000000000000000000000000000000000000000000000000000000000000000000000000000000000000000000000000000000000000000000000000000000000000000000000000000000000000000000000000000000000000000000000000000000000000000000000000000000000000000000000000000000000000000000000000000000000000000000000000000000000000000000000000000000000000000000000000000000000000000000000000000000000000000000000000000000000000000000000000000000000000000000000000000000000000000000000000000000000000000000000000000 (
1&
1$
#19500000
0$
#19750000
b100000000000000 )
b100110010011001001100100110000000000000010011 %
b10011 #
b10011 "
b10010 !
0&
1$
#20000000
0$
#20250000
b10011001001100100110010011000000000000001001100000000000000000000000000000000000000000000000000000000000000000000000000000000000000000000000000000000000000000000000000000000000000000000000000000000000000000000000000000000000000000000000000000000000000000000000000000000000000000000000000000000000000000000000000000000000000000000000000000000000000000000000000000000000000000000000000000000000000000000000000000000000000000000000000000000000000000000000000000000000000000000000000000000000000000000000000000000000000000000000000000000000000000000000000000000000000000000000000000000000000000000000000000000000000000000000000000000000000000000000000000000000000000000000000000000000000000000000000000000000000000000000000000000000000000000000000000000000000000000000000000000000000000000000000000000000000000000000000000000000000000000000000000000000000000000000000000000000000000000000000000000000000000000000000000000000000000000000000000000 (
1&
1$
#20500000
0$
#20750000
b1000000000 )
b101000010100001010000101000000000000000010100 %
b10100 #
b10100 "
b10011 !
0&
1$
#21000000
0$
#21250000
b101000010100001010000101000000000000000010100000000000000000000000000000000000000000000000000000000000000000000000000000000000000000000000000000000000000000000000000000000000000000000000000000000000000000000000000000000000000000000000000000000000000000000000000000000000000000000000000000000000000000000000000000000000000000000000000000000000000000000000000000000000000000000000000000000000000000000000000000000000000000000000000000000000000000000000000000000000000000000000000000000000000000000000000000000000000000000000000000000000000000000000000000000000000000000000000000000000000000000000000000000000000000000000000 (
1&
1$
#21500000
0$
#21750000
b10000000000000 )
b101010010101001010100101010000000000000010101 %
b10101 #
b10101 "
b10100 !
0&
1$
#22000000
0$
#22250000
b1010100101010010101001010100000000000000101010000000000000000000000000000000000000000000000000000000000000000000000000000000000000000000000000000000000000000000000000000000000000000000000000000000000000000000000000000000000000000000000000000000000000000000000000000000000000000000000000000000000000000000000000000000000000000000000000000000000000000000000000000000000000000000000000000000000000000000000000000000000000000000000000000000000000000000000000000000000000000000000000000000000000000000000000000000000000000000000000000000000000000000000000000000000000000000000000000000000000000000000000000000000000000000000000000000000000000000000000000000000000000000000000000000000000000000000000000000000000000000000000000000000000000000000000000000000000000000000000000000000000000000000000000000000000000000000000000000000000000000000000000000000000000000000000000000000000000 (
1&
1$
#22500000
0$
#22750000
b100000000000 )
b101100010110001011000101100000000000000010110 %
b10110 #
b10110 "
b10101 !
0&
1$
#23000000
0$
#23250000
b10110001011000101100010110000000000000001011000000000000000000000000000000000000000000000000000000000000000000000000000000000000000000000000000000000000000000000000000000000000000000000000000000000000000000000000000000000000000000000000000000000000000000000000000000000000000000000000000000000000000000000000000000000000000000000000000000000000000000000000000000000000000000000000000000000000000000000000000000000000000000000000000000000000000000000000000000000000000000000000000000000000000000000000000000000000000000000000000000000000000000000000000000000000000000000000000000000000000000000000000000000000000000000000000000000000000000000000000000000000000000000000000000000000000000000000000000000000000000000000000000000000000000000000000000000 (
1&
1$
#23500000
0$
#23750000
b1000000000000000 )
b101110010111001011100101110000000000000010111 %
b10111 #
b10111 "
b10110 !
0&
1$
#24000000
0$
#24250000
b101110010111001011100101110000000000000010111000000000000000000000000000000000000000000000000000000000000000000000000000000000000000000000000000000000000000000000000000000000000000000000000000000000000000000000000000000000000000000000000000000000000000000000000000000000000000000000000000000000000000000000000000000000000000000000000000000000000000000000000000000000000000000000000000000000000000000000000000000000000000000000000000000000000000000000000000000000000000000000000000000000000000000000000000000000000000000000000000000000000000000000000000000000000000000000000000000000000000000000000000000000000000000000000000000000000000000000000000000000000000000000000000000000000000000000000000000000000000000000000000000000000000000000000000000000000000000000000000000000000000000000000000000000000000000000000000000000000000000000000000000000000000000000000000000000000000000000000000000000000000000000000000000000000000000000000000000000000000000000000000000000000000000000000000000000000000000000000 (
1&
1$
#24500000
0$
#24750000
b1000000000000000000000000 )
b110000011000001100000110000000000000000011000 %
b11000 #
b11000 "
b10111 !
0&
1$
#25000000
0$
#25250000
b110000011000001100000110000000000000000011000 *
b110000011000001100000110000000000000000011000000000000000000000000000000000000000000000000000000000000000000000000000000000000000000000000000000000000000000000000000000000000000000000000000000000000000000000000000000000000000000000000000000000000000000000000000000000000000000000000000000000000000000000000000000000000000000000000000000000000000000000000000000000000000000000000000000000000000000000000000000000000000000000000000000000000000000000000000000000000000000000000000000000000000000000000000000000000000000000000000000000000000000000000000000000000000000000000000000000000000000000000000000000000000000000000000000000000000000000000000000000000000000000000000000000000000000000000000000000000000000000000000000000000000000000000000000000000000000000000000000000000000000000000000000000000000000000000000000000000000000000000000000000000000000000000000000000000000000000000000000000000000000000000000000000000000000000000000000000000000000000000000000000000000000000000000000000000000000000000000000000000000000000000000000000000000000000000000000000000000000000000000000000000000000000000000000000000000000000000000000000000000000000000000000000000000000000000000000000000000000000000000000000000000000000000000000000000000000000000000000000000000000000000000000000000000000000000000000000000000000000000000000000000000000000000000000000000000000000000000000000000000000000000000000000000000000000000000000000000000000000000000000000000000000000000000000000000000000000000000000000000000000000000000000000000000000000000000000000000000000000000000000000000000000000000000 (
1&
1$
#25500000
0$
#25750000
b10000000000000000000000000000 )
b110010011001001100100110010000000000000011001 %
b11001 #
b0 *
b11001 "
b110000011000001100000110000000000000000011000 +
b11000 !
0&
1$
#26000000
0$
#26250000
b0 +
b1100100110010011001001100100000000000000110010000000000000000000000000000000000000000000000000000000000000000000000000000000000000000000000000000000000000000000000000000000000000000000000000000000000000000000000000000000000000000000000000000000000000000000000000000000000000000000000000000000000000000000000000000000000000000000000000000000000000000000000000000000000000000000000000000000000000000000000000000000000000000000000000000000000000000000000000000000000000000000000000000000000000000000000000000000000000000000000000000000000000000000000000000000000000000000000000000000000000000000000000000000000000000000000000000000000000000000000000000000000000000000000000000000000000000000000000000000000000000000000000000000000000000000000000000000000000000000000000000000000000000000000000000000000000000000000000000000000000000000000000000000000000000000000000000000000000000000000000000000000000000000000000000000000000000000000000000000000000000000000000000000000000000000000000000000000000000000000000000000000000000000000000000000000000000000000000000000000000000000000000000000000000000000000000000000000000000000000000000000000000000000000000000000000000000000000000000000000000000000000000000000000000000000000000000000000000000000000000000000000000000000000000000000000000000000000000000000000000000000000000000000000000000000000000000000000000000000000000000000000000000000000000000000000000000000000000000000000000000000000000000000000000000000000000000000000000000000000000000000000000000000000000000000000000000000000000000000000000000000000000000000000000000000000000000000000000000000000000000000000000000000000000000000000000000000000000000000000000000000000000000000000000000000000000000000000000000000000000000000000000000000000000000000000000000000000000000000000000000000000000000000000000000000000000000000000000000 (
1&
1$
#26500000
0$
#26750000
b100000000000000000000000000 )
b110100011010001101000110100000000000000011010 %
b11010 #
b11010 "
b11001 !
0&
1$
#27000000
0$
