lab2/verilog/mux2to1.v
module mux2to1 (i1, i0, out, en);
	output wire out;

	input i0, i1, en;

	wire ren;
	wire [1:0] con;

	not (ren, en);

	and (con[0], en, i1);
	and (con[1], ren, i0);
	
	or (out, con[0], con[1]);
	
endmodule

lab2/verilog/complement.v
`include "mux2to1.v"

module complement (in, out, en);
	output [63:0] out;

	input [63:0] in;
	input en;

	wire [63:0] temp;

	generate
		genvar i;
		for (i = 0; i < 64; i = i + 1) begin
			not (temp[i], in[i]);
			mux2to1 sel (temp[i], in[i], out[i], en);
		end
	endgenerate

endmodule

lab2/verilog/tb_complement.v
`include "complement.v"

module tb_complement();
	wire [63:0] out;

	reg [63:0] in;
	reg en;

	complement dut(in, out, en);

	initial begin
		$dumpfile("complement_wave.vcd");
		$dumpvars(1, dut);
	end

	integer i, j;
	initial begin
		en <= 1;
		for (i = 0; i < 10; i = i + 1) begin
			in <= i * 64'd1235312;
			#5;
		end
		en <= 0;
		for (j = 0; j < 10; j = j + 1) begin
			in <= j * 64'd1235312;
			#5;
		end
		$stop;
	end
endmodule

lab2/verilog/complement_wave.vcd
$date
	Thu Jan 25 14:55:55 2018
$end
$version
	Icarus Verilog
$end
$timescale
	1s
$end
$scope module tb_complement $end
$scope module dut $end
$var wire 1 ! en $end
$var wire 64 " in [63:0] $end
$var wire 64 # temp [63:0] $end
$var wire 64 $ out [63:0] $end
$upscope $end
$upscope $end
$enddefinitions $end
#0
$dumpvars
b1111111111111111111111111111111111111111111111111111111111111111 $
b1111111111111111111111111111111111111111111111111111111111111111 #
b0 "
1!
$end
#5
b1111111111111111111111111111111111111111111011010010011010001111 $
b1111111111111111111111111111111111111111111011010010011010001111 #
b100101101100101110000 "
#10
b1111111111111111111111111111111111111111110110100100110100011111 $
b1111111111111111111111111111111111111111110110100100110100011111 #
b1001011011001011100000 "
#15
b1111111111111111111111111111111111111111110001110111001110101111 $
b1111111111111111111111111111111111111111110001110111001110101111 #
b1110001000110001010000 "
#20
b1111111111111111111111111111111111111111101101001001101000111111 $
b1111111111111111111111111111111111111111101101001001101000111111 #
b10010110110010111000000 "
#25
b1111111111111111111111111111111111111111101000011100000011001111 $
b1111111111111111111111111111111111111111101000011100000011001111 #
b10111100011111100110000 "
#30
b1111111111111111111111111111111111111111100011101110011101011111 $
b1111111111111111111111111111111111111111100011101110011101011111 #
b11100010001100010100000 "
#35
b1111111111111111111111111111111111111111011111000000110111101111 $
b1111111111111111111111111111111111111111011111000000110111101111 #
b100000111111001000010000 "
#40
b1111111111111111111111111111111111111111011010010011010001111111 $
b1111111111111111111111111111111111111111011010010011010001111111 #
b100101101100101110000000 "
#45
b1111111111111111111111111111111111111111010101100101101100001111 $
b1111111111111111111111111111111111111111010101100101101100001111 #
b101010011010010011110000 "
#50
b0 $
b1111111111111111111111111111111111111111111111111111111111111111 #
b0 "
0!
#55
b100101101100101110000 $
b1111111111111111111111111111111111111111111011010010011010001111 #
b100101101100101110000 "
#60
b1001011011001011100000 $
b1111111111111111111111111111111111111111110110100100110100011111 #
b1001011011001011100000 "
#65
b1110001000110001010000 $
b1111111111111111111111111111111111111111110001110111001110101111 #
b1110001000110001010000 "
#70
b10010110110010111000000 $
b1111111111111111111111111111111111111111101101001001101000111111 #
b10010110110010111000000 "
#75
b10111100011111100110000 $
b1111111111111111111111111111111111111111101000011100000011001111 #
b10111100011111100110000 "
#80
b11100010001100010100000 $
b1111111111111111111111111111111111111111100011101110011101011111 #
b11100010001100010100000 "
#85
b100000111111001000010000 $
b1111111111111111111111111111111111111111011111000000110111101111 #
b100000111111001000010000 "
#90
b100101101100101110000000 $
b1111111111111111111111111111111111111111011010010011010001111111 #
b100101101100101110000000 "
#95
b101010011010010011110000 $
b1111111111111111111111111111111111111111010101100101101100001111 #
b101010011010010011110000 "
