lab2/verilog/gateLogic.v
module zero (in, out);
	output out;

	input [63:0] in;

	wire [15:0] t0;
	wire [3:0] t1;

	generate
		genvar i;
		for (i = 0; i < 16; i = i + 1) begin
			nor (t0[i], in[i*0], in[i*0+1], in[i*0+2], in[i*0+3]);
		end
	endgenerate
	
	generate
		genvar j;
		for (j = 0; j < 4; j = j + 1) begin
			nor (t1[j], t0[j*0], t0[j*0+1], t0[j*0+2], t0[j*0+3]);
		end
	endgenerate

	nor (out, t1[1], t1[0], t1[2], t1[3]);
endmodule

module bitAND (A, B, out);
	output [63:0] out;

	input [63:0] A, B;

	generate
		genvar i;
		for (i = 0; i < 64; i = i + 1) begin
			and (out[i], A[i], B[i]);
		end
	endgenerate
endmodule

module bitOR (A, B, out);
	output [63:0] out;

	input [63:0] A, B;

	generate
		genvar i;
		for (i = 0; i < 64; i = i + 1) begin
			or (out[i], A[i], B[i]);
		end
	endgenerate
endmodule

module bitXOR (A, B, out);
	output [63:0] out;

	input [63:0] A, B;

	generate
		genvar i;
		for (i = 0; i < 64; i = i + 1) begin
			xor (out[i], A[i], B[i]);
		end
	endgenerate
endmodule

lab2/verilog/tb_gateLogic.v
`include "gateLogic.v"

module tb_gateLogic();
	wire NORout;
	wire [63:0] out;

	reg [63:0] A, B;

	initial begin
		$dumpfile("gateLogic_wave.vcd");
		$dumpvars(1, dut0);
		$dumpvars(1, dut1);
		$dumpvars(1, dut2);
		$dumpvars(1, dut3);
	end

	zero dut0 (A, NORout);
	bitAND dut1 (A, B, out);
	bitOR dut2 (A, B, out);
	bitXOR dut3 (A, B, out);

	integer i, j;
	integer seed = 1;
	initial begin
		for (i = 0; i < 32; i = i + 1) begin
			A <= i * 64'd12353;
			B <= i * 64'd12353 + i;
			#5;
		end
		A <= 64'b0;
		#5;
		repeat (10) begin
			A <= $random(seed); B <= $random(seed);
			#5;
		end
		$stop;
	end

endmodule

lab2/verilog/tb_gateLogic.vcd
$date
	Fri Jan 26 14:38:04 2018
$end
$version
	Icarus Verilog
$end
$timescale
	1s
$end
$scope module tb_gateLogic $end
$scope module dut0 $end
$var wire 64 ! in [63:0] $end
$var wire 1 " out $end
$var wire 4 # t1 [3:0] $end
$var wire 16 $ t0 [15:0] $end
$upscope $end
$upscope $end
$scope module tb_gateLogic $end
$scope module dut1 $end
$var wire 64 % A [63:0] $end
$var wire 64 & B [63:0] $end
$var wire 64 ' out [63:0] $end
$upscope $end
$upscope $end
$scope module tb_gateLogic $end
$scope module dut2 $end
$var wire 64 ( A [63:0] $end
$var wire 64 ) B [63:0] $end
$var wire 64 * out [63:0] $end
$upscope $end
$upscope $end
$scope module tb_gateLogic $end
$scope module dut3 $end
$var wire 64 + A [63:0] $end
$var wire 64 , B [63:0] $end
$var wire 64 - out [63:0] $end
$upscope $end
$upscope $end
$enddefinitions $end
#0
$dumpvars
b0 -
b0 ,
b0 +
b0 *
b0 )
b0 (
b0 '
b0 &
b0 %
b1111111111111111 $
b0 #
1"
b0 !
$end
#5
b1111111111110100 $
b0xx00000x0000xx '
b0xx00000x0000xx *
b0xx00000x0000xx -
b11000001000010 &
b11000001000010 )
b11000001000010 ,
b11000001000001 !
b11000001000001 %
b11000001000001 (
b11000001000001 +
#10
b0xx00000x0000xx0 '
b0xx00000x0000xx0 *
b0xx00000x0000xx0 -
b110000010000100 &
b110000010000100 )
b110000010000100 ,
b110000010000010 !
b110000010000010 %
b110000010000010 (
b110000010000010 +
#15
b0x00x0000xx000xxx '
b0x00x0000xx000xxx *
b0x00x0000xx000xxx -
b1001000011000110 &
b1001000011000110 )
b1001000011000110 ,
b1001000011000011 !
b1001000011000011 %
b1001000011000011 (
b1001000011000011 +
#20
b1111111111110010 $
b0xx00000x0000xx00 '
b0xx00000x0000xx00 *
b0xx00000x0000xx00 -
b1100000100001000 &
b1100000100001000 )
b1100000100001000 ,
b1100000100000100 !
b1100000100000100 %
b1100000100000100 (
b1100000100000100 +
#25
0"
b1 #
b1111111111110000 $
b0xxxx000x0x00xxxx '
b0xxxx000x0x00xxxx *
b0xxxx000x0x00xxxx -
b1111000101001010 &
b1111000101001010 )
b1111000101001010 ,
b1111000101000101 !
b1111000101000101 %
b1111000101000101 (
b1111000101000101 +
#30
b1111111111100000 $
b0x00x0000xx000xxx0 '
b0x00x0000xx000xxx0 *
b0x00x0000xx000xxx0 -
b10010000110001100 &
b10010000110001100 )
b10010000110001100 ,
b10010000110000110 !
b10010000110000110 %
b10010000110000110 (
b10010000110000110 +
#35
b0x0x0x000xxx00xxxx '
b0x0x0x000xxx00xxxx *
b0x0x0x000xxx00xxxx -
b10101000111001110 &
b10101000111001110 )
b10101000111001110 ,
b10101000111000111 !
b10101000111000111 %
b10101000111000111 (
b10101000111000111 +
#40
1"
b0 #
b1111111111100010 $
b0xx00000x0000xx000 '
b0xx00000x0000xx000 *
b0xx00000x0000xx000 -
b11000001000010000 &
b11000001000010000 )
b11000001000010000 ,
b11000001000001000 !
b11000001000001000 %
b11000001000001000 (
b11000001000001000 +
#45
0"
b1 #
b1111111111100000 $
b0xx0xx00x00x0xx0xx '
b0xx0xx00x00x0xx0xx *
b0xx0xx00x00x0xx0xx -
b11011001001010010 &
b11011001001010010 )
b11011001001010010 ,
b11011001001001001 !
b11011001001001001 %
b11011001001001001 (
b11011001001001001 +
#50
b0xxxx000x0x00xxxx0 '
b0xxxx000x0x00xxxx0 *
b0xxxx000x0x00xxxx0 -
b11110001010010100 &
b11110001010010100 )
b11110001010010100 ,
b11110001010001010 !
b11110001010001010 %
b11110001010001010 (
b11110001010001010 +
#55
b0x0000x00x0xx0xxxxx '
b0x0000x00x0xx0xxxxx *
b0x0000x00x0xx0xxxxx -
b100001001011010110 &
b100001001011010110 )
b100001001011010110 ,
b100001001011001011 !
b100001001011001011 %
b100001001011001011 (
b100001001011001011 +
#60
1"
b0 #
b1111111111100010 $
b0x00x0000xx000xxx00 '
b0x00x0000xx000xxx00 *
b0x00x0000xx000xxx00 -
b100100001100011000 &
b100100001100011000 )
b100100001100011000 ,
b100100001100001100 !
b100100001100001100 %
b100100001100001100 (
b100100001100001100 +
#65
0"
b1 #
b1111111111100000 $
b0x00xxx00xx0x0xxxxx '
b0x00xxx00xx0x0xxxxx *
b0x00xxx00xx0x0xxxxx -
b100111001101011010 &
b100111001101011010 )
b100111001101011010 ,
b100111001101001101 !
b100111001101001101 %
b100111001101001101 (
b100111001101001101 +
#70
b0x0x0x000xxx00xxxx0 '
b0x0x0x000xxx00xxxx0 *
b0x0x0x000xxx00xxxx0 -
b101010001110011100 &
b101010001110011100 )
b101010001110011100 ,
b101010001110001110 !
b101010001110001110 %
b101010001110001110 (
b101010001110001110 +
#75
b0x0xx0x00xxxx0xxxxx '
b0x0xx0x00xxxx0xxxxx *
b0x0xx0x00xxxx0xxxxx -
b101101001111011110 &
b101101001111011110 )
b101101001111011110 ,
b101101001111001111 !
b101101001111001111 %
b101101001111001111 (
b101101001111001111 +
#80
1"
b0 #
b1111111111101001 $
b0xx00000x0000xx0000 '
b0xx00000x0000xx0000 *
b0xx00000x0000xx0000 -
b110000010000100000 &
b110000010000100000 )
b110000010000100000 ,
b110000010000010000 !
b110000010000010000 %
b110000010000010000 (
b110000010000010000 +
#85
0"
b1 #
b1111111111100000 $
b0xx00xx0x000xxx00xx '
b0xx00xx0x000xxx00xx *
b0xx00xx0x000xxx00xx -
b110011010001100010 &
b110011010001100010 )
b110011010001100010 ,
b110011010001010001 !
b110011010001010001 %
b110011010001010001 (
b110011010001010001 +
#90
b0xx0xx00x00x0xx0xx0 '
b0xx0xx00x00x0xx0xx0 *
b0xx0xx00x00x0xx0xx0 -
b110110010010100100 &
b110110010010100100 )
b110110010010100100 ,
b110110010010010010 !
b110110010010010010 %
b110110010010010010 (
b110110010010010010 +
#95
b0xxx00x0x00xxxx0xxx '
b0xxx00x0x00xxxx0xxx *
b0xxx00x0x00xxxx0xxx -
b111001010011100110 &
b111001010011100110 )
b111001010011100110 ,
b111001010011010011 !
b111001010011010011 %
b111001010011010011 (
b111001010011010011 +
#100
b0xxxx000x0x00xxxx00 '
b0xxxx000x0x00xxxx00 *
b0xxxx000x0x00xxxx00 -
b111100010100101000 &
b111100010100101000 )
b111100010100101000 ,
b111100010100010100 !
b111100010100010100 %
b111100010100010100 (
b111100010100010100 +
#105
b0xxxxxx0x0x0xxxxxxx '
b0xxxxxx0x0x0xxxxxxx *
b0xxxxxx0x0x0xxxxxxx -
b111111010101101010 &
b111111010101101010 )
b111111010101101010 ,
b111111010101010101 !
b111111010101010101 %
b111111010101010101 (
b111111010101010101 +
#110
b0x0000x00x0xx0xxxxx0 '
b0x0000x00x0xx0xxxxx0 *
b0x0000x00x0xx0xxxxx0 -
b1000010010110101100 &
b1000010010110101100 )
b1000010010110101100 ,
b1000010010110010110 !
b1000010010110010110 %
b1000010010110010110 (
b1000010010110010110 +
#115
b0x000x0x0x0xxxxxxxxx '
b0x000x0x0x0xxxxxxxxx *
b0x000x0x0x0xxxxxxxxx -
b1000101010111101110 &
b1000101010111101110 )
b1000101010111101110 ,
b1000101010111010111 !
b1000101010111010111 %
b1000101010111010111 (
b1000101010111010111 +
#120
b0x00x0000xx000xxx000 '
b0x00x0000xx000xxx000 *
b0x00x0000xx000xxx000 -
b1001000011000110000 &
b1001000011000110000 )
b1001000011000110000 ,
b1001000011000011000 !
b1001000011000011000 %
b1001000011000011000 (
b1001000011000011000 +
#125
b0x00x0xx0xx00xxxx0xx '
b0x00x0xx0xx00xxxx0xx *
b0x00x0xx0xx00xxxx0xx -
b1001011011001110010 &
b1001011011001110010 )
b1001011011001110010 ,
b1001011011001011001 !
b1001011011001011001 %
b1001011011001011001 (
b1001011011001011001 +
#130
b0x00xxx00xx0x0xxxxx0 '
b0x00xxx00xx0x0xxxxx0 *
b0x00xxx00xx0x0xxxxx0 -
b1001110011010110100 &
b1001110011010110100 )
b1001110011010110100 ,
b1001110011010011010 !
b1001110011010011010 %
b1001110011010011010 (
b1001110011010011010 +
#135
b0x0x000x0xx0xxxxxxxx '
b0x0x000x0xx0xxxxxxxx *
b0x0x000x0xx0xxxxxxxx -
b1010001011011110110 &
b1010001011011110110 )
b1010001011011110110 ,
b1010001011011011011 !
b1010001011011011011 %
b1010001011011011011 (
b1010001011011011011 +
#140
b0x0x0x000xxx00xxxx00 '
b0x0x0x000xxx00xxxx00 *
b0x0x0x000xxx00xxxx00 -
b1010100011100111000 &
b1010100011100111000 )
b1010100011100111000 ,
b1010100011100011100 !
b1010100011100011100 %
b1010100011100011100 (
b1010100011100011100 +
#145
b0x0x0xxx0xxx0xxxxxxx '
b0x0x0xxx0xxx0xxxxxxx *
b0x0x0xxx0xxx0xxxxxxx -
b1010111011101111010 &
b1010111011101111010 )
b1010111011101111010 ,
b1010111011101011101 !
b1010111011101011101 %
b1010111011101011101 (
b1010111011101011101 +
#150
b0x0xx0x00xxxx0xxxxx0 '
b0x0xx0x00xxxx0xxxxx0 *
b0x0xx0x00xxxx0xxxxx0 -
b1011010011110111100 &
b1011010011110111100 )
b1011010011110111100 ,
b1011010011110011110 !
b1011010011110011110 %
b1011010011110011110 (
b1011010011110011110 +
#155
b0x0xxx0x0xxxxxxxxxxx '
b0x0xxx0x0xxxxxxxxxxx *
b0x0xxx0x0xxxxxxxxxxx -
b1011101011111111110 &
b1011101011111111110 )
b1011101011111111110 ,
b1011101011111011111 !
b1011101011111011111 %
b1011101011111011111 (
b1011101011111011111 +
#160
1"
b0 #
b1111111111111111 $
b0x0xxx0x0xxxxxxxxxx0 '
b0x0xxx0x0xxxxxxxxxx0 *
b0x0xxx0x0xxxxxxxxxx0 -
b0 !
b0 %
b0 (
b0 +
