lab3/verilog/ALUcontrol.v
`timescale 1ns/10ps

module ALUcontrol(instruct, Op, out);
	output [2:0] out;

	input [10:0] instruct;
	input [1:0] Op;

	wire [7:0] F;

	assign F = instruct[10:6];

	wire [1:0] t0;

	// always @(*) begin
	// 	casez(Op)
	// 		2'b00: out = 3'b010;
	// 		2'bZ1: out = 3'b111;
	// 		2'b1Z: if (instruct[9] == 0 && instruct[3] == 1)
	// 					out = 3'b010;
	// 				else if (instruct[9] == 1 && instruct[3] == 1)
	// 					out = 3'b110;
	// 				else if (instruct[8])
	// 					out = 3'b001;
	// 				else 
	// 					out = 0;
	// 	endcase
	// end

	//Operation 0
	or  (t0[0], F[3], F[0]);
	and  (out[0], Op[1], t0[0]);

	//Operation 1
	nor  (out[1], Op[1], F[2]);

	//operation 2
	and  (t0[1], F[1], Op[1]);
	or  (out[2], Op[0], t0[1]);


endmodule

lab3/verilog/tb_ALUcontrol.v
`include "ALUcontrol.v"

module tb_ALUcontrol();
	wire [2:0] out;

	reg [10:0] instruct;
	reg [1:0] Op;

	ALUcontrol dut (instruct, Op, out);

	initial begin
		$dumpfile("ALUcontrol_wave.vcd");
		$dumpvars(1, dut);
	end

	integer i, j;
	initial begin
		for (i = 0; i < 4; i = i + 1) begin
			Op <= i;
			instruct <= 11'b1xx01x000;
			#5;
			instruct <= 11'b11111000010;
			#5;
			instruct <= 11'b11111000000;
			#5;
			instruct <= 11'b10110100xxx;
			#5;	
		end		
		$stop;
	end
endmodule

lab3/verilog/ALUcontrol_wave.vcd
$date
	Fri Feb 09 12:10:05 2018
$end
$version
	Icarus Verilog
$end
$timescale
	10ps
$end
$scope module tb_ALUcontrol $end
$scope module dut $end
$var wire 2 ! Op [1:0] $end
$var wire 11 " instruct [10:0] $end
$var wire 2 # t0 [1:0] $end
$var wire 3 $ out [2:0] $end
$var wire 8 % F [7:0] $end
$upscope $end
$upscope $end
$enddefinitions $end
#0
$dumpvars
b1xx %
b0 $
b0x #
b1xx01x000 "
b0 !
$end
#500
b1 #
b11111 %
b11111000010 "
#1000
b11111000000 "
#1500
b0 #
b10110 %
b10110100xxx "
#2000
b0x #
b100 $
b1xx %
b1xx01x000 "
b1 !
#2500
b1 #
b11111 %
b11111000010 "
#3000
b11111000000 "
#3500
b0 #
b10110 %
b10110100xxx "
#4000
bx #
bx0x $
b1xx %
b1xx01x000 "
b10 !
#4500
b101 $
b11 #
b11111 %
b11111000010 "
#5000
b11111000000 "
#5500
b100 $
b10 #
b10110 %
b10110100xxx "
#6000
b10x $
bx #
b1xx %
b1xx01x000 "
b11 !
#6500
b101 $
b11 #
b11111 %
b11111000010 "
#7000
b11111000000 "
#7500
b100 $
b10 #
b10110 %
b10110100xxx "
