lab3/verilog/gateLogic.v
`timescale 1ns/10ps

module zero (in, out);
	output out;

	input [63:0] in;

	wire [15:0] t0;
	wire [3:0] t1;

	generate
		genvar i;
		for (i = 0; i < 16; i = i + 1) begin
			or #50 (t0[i], in[i*4], in[i*4+1], in[i*4+2], in[i*4+3]);
		end
	endgenerate
	
	generate
		genvar j;
		for (j = 0; j < 4; j = j + 1) begin
			or #50 (t1[j], t0[j*4], t0[j*4+1], t0[j*4+2], t0[j*4+3]);
		end
	endgenerate

	nor (out, t1[0], t1[1], t1[2], t1[3]);
endmodule

module bitAND (A, B, out);
	output [63:0] out;

	input [63:0] A, B;

	generate
		genvar i;
		for (i = 0; i < 64; i = i + 1) begin
			and #50 (out[i], A[i], B[i]);
		end
	endgenerate
endmodule

module bitOR (A, B, out);
	output [63:0] out;

	input [63:0] A, B;

	generate
		genvar i;
		for (i = 0; i < 64; i = i + 1) begin
			or #50 (out[i], A[i], B[i]);
		end
	endgenerate
endmodule

module bitXOR (A, B, out);
	output [63:0] out;

	input [63:0] A, B;

	generate
		genvar i;
		for (i = 0; i < 64; i = i + 1) begin
			xor #50 (out[i], A[i], B[i]);
		end
	endgenerate
endmodule

lab1/D_FF.v
module D_FF (q, d, reset, clk);
  output reg q;
  input d, reset, clk;

  always @(posedge clk)
  if (reset)
    q <= 0;  // On reset, set to 0
  else
    q <= d; // Otherwise out = d
endmodule

lab1/register.v
`include "D_FF.v"

module register (in, out, en, clk);
	output [63:0] out;

	input [63:0] in;
	input en, clk;

	wire [63:0] temp, old;

	assign old = out;
	generate
		genvar i; 
		for (i = 0; i < 64; i = i + 1'b1) begin
			mux2to1 choose (.new(in[i]), .old(old[i]), .out(temp[i]), .en(en));
			D_FF set (.q(out[i]), .d(temp[i]), .reset(1'b0), .clk(clk));
		end
	endgenerate
endmodule

module mux2to1 (new, old, out, en);
	output wire out;

	input new, old, en;

	wire ren;
	wire [1:0] con;

	not ren0 (ren, en);

	and con0 (con[0], en, new);
	and con1 (con[1], ren, old);
	
	or out0 (out, con[0], con[1]);
	
	//assign out = (en & new) | (~en & old);

endmodule

lab2/mux5to1.sv

module mux5to1 (ADD, AND, XOR, OR, B, out, sel);
	output [63:0] out;

	input [63:0] ADD, AND, XOR, OR, B;
	input [2:0] sel;

	wire [2:0][63:0] t0;

	generate
		genvar i;
		for (i = 0; i < 64; i = i + 1) begin : decide
			mux2to1 ANDtoOR (OR[i], AND[i], t0[0][i], sel[0]);
			mux2to1 XORsel (XOR[i], t0[0][i], t0[1][i], sel[1]);
			mux2to1 BtoADD (ADD[i], B[i], t0[2][i], sel[1]);
			mux2to1 finale (t0[1][i], t0[2][i], out[i], sel[2]);
		end
	endgenerate

endmodule

lab3/verilog/fullADD.v
`timescale 1ns/10ps

module adder (i0, i1, Ci, Co, S);
	output S, Co;

	input i0, i1, Ci;

	wire temp0;
	wire [1:0] temp1;

	xor #50 (temp0, i1, i0);
	xor #50 (S, temp0, Ci);

	and #50 (temp1[0], Ci, temp0);
	and #50 (temp1[1], i0, i1);

	or #50 (Co, temp1[0], temp1[1]);
endmodule

lab3/arithmetic.v
`include "fullADD.v"
`timescale 1ns/10ps
module arithmetic (A, B, out, of, C, sub);
	output [63:0] out;
	output of, C;

	input [63:0] A, B;
	input sub;

	wire [64:0] C0;
	wire [63:0] Btemp;
	
	xor (C0[0], sub, 1'b0);

	generate
		genvar i;
		for (i = 0; i < 64; i = i + 1) begin
			xor (Btemp[i], sub, B[i]);
			adder add (A[i], Btemp[i], C0[i], C0[i + 1], out[i]);
		end
	endgenerate

	xor #50 (C, C0[64], sub);
	xor #50 (of, C0[63], C0[64]);

endmodule

// module adder (A, B, Ci, Co, S);
// 	output S, Co;

// 	input A, B, Ci;

// 	wire temp0;
// 	wire [1:0] temp1;

// 	xor (temp0, A, B);
// 	xor (S, temp0, Ci);

// 	and (temp1[0], Ci, temp0);
// 	and (temp1[1], A, B);

// 	or (Co, temp1[0], temp1[1]);
// endmodule

lab3/verilog/alu.v
`include "arithmetic.v"
`include "mux5to1.v"
`include "gateLogic.v"
`timescale 1ns/10ps

module alu (A, B, cntrol, result, negative, zero, overflow, carry_out);
	input [63:0] A, B;
	input [2:0] cntrol;

	output negative, zero, overflow, carry_out;
	output [63:0] result;

	wire [63:0] tB, ADD, AND, XOR, OR;
	wire t0, c, of, ncntrl;

	bitAND ANDbit (A, B, AND);
	bitOR ORbit (A, B, OR);
	bitXOR XORbit (A, B, XOR);

	arithmetic ADDorSUB (A, B, ADD, of, c, cntrol[0]); 
	mux5to1 choose (ADD, AND, XOR, OR, B, result, cntrol);

	not #50 (ncntrol, cntrol[2]);
	and #50 (t0, ncntrol, cntrol[1]);
	mux2to1 carry (c, 1'b0, carry_out, t0);
	mux2to1 flow (of, 1'b0, overflow, t0);
	zero check (result, zero);
	assign negative = result[63];
endmodule

lab3/programCounter.v
`timescale 1ns/10ps

module programCounter(in, PCsrc, out, clk, reset);
	output reg [63:0] out;

	input [63:0] in;
	input clk, reset, PCsrc;

	wire [63:0] B, PC4, temp;
	wire C, of, neg, z;

	alu bcond (temp, in, 3'b010, B, C, of, neg, z);
	alu pc4 (temp, 64'd4, 3'b010, PC4, C, of, neg, z);

	always @(posedge clk) begin
		if (reset)
			out <= 0;
		else if (PCsrc)
			out <= B;
		else begin
			out <= PC4;
		end
	end
	assign temp = out;
endmodule

lab3/verilog/tb_programCounter.v
`include "programCounter.v"

module tb_programCounter();
	wire [63:0] out;

	reg [63:0] in;
	reg clk, reset, PCsrc;

	parameter ClockDelay = 5000;

	programCounter dut (in, PCsrc, out, clk, reset);

	initial begin
		$dumpfile("programCounter_wave.vcd");
		$dumpvars(1, dut);
	end

	initial begin // Set up the clock
		clk <= 0;
		forever #(ClockDelay/2) clk <= ~clk;
	end

	integer i;
	initial begin
		reset <=1; PCsrc <= 0; @(posedge clk);
		reset <=0;
		for (i = 0; i < 11; i++) begin
			in <= i*64'h12FF3CA146;
			@(posedge clk);
		end
		PCsrc <= 1;
		repeat(10) begin
			@(posedge clk);
		end
		$stop;
	end

endmodule

lab3/verilog/programCounter_wave.vcd
$date
	Fri Feb 09 10:57:49 2018
$end
$version
	Icarus Verilog
$end
$timescale
	10ps
$end
$scope module tb_programCounter $end
$scope module dut $end
$var wire 1 ! C $end
$var wire 1 " PCsrc $end
$var wire 1 # clk $end
$var wire 64 $ in [63:0] $end
$var wire 1 % neg $end
$var wire 1 & of $end
$var wire 1 ' reset $end
$var wire 64 ( temp [63:0] $end
$var wire 1 ) z $end
$var wire 64 * PC4 [63:0] $end
$var wire 64 + B [63:0] $end
$var reg 64 , out [63:0] $end
$upscope $end
$upscope $end
$enddefinitions $end
#0
$dumpvars
bx ,
bx +
bx *
x)
bx (
1'
x&
x%
bx $
0#
0"
x!
$end
#250000
b0 (
b0 ,
b0 $
0'
1#
#280000
bx0 +
bx100 *
0)
0%
#285000
bx00 +
bx0100 *
#290000
0!
b0 +
b100 *
#500000
0#
#750000
b1001011111111001111001010000101000110 $
b100 (
b100 ,
1#
#780000
b1001011111111001111001010000101000010 +
b0 *
#785000
b1001011111111001111001010000101001010 +
b1000 *
#790000
x&
#795000
0&
#1000000
0#
#1250000
b1000 (
b1000 ,
b10010111111110011110010100001010001100 $
1#
#1280000
b10010111111110011110010100001010001100 +
b100 *
#1285000
b10010111111110011110010100001010010100 +
b1100 *
#1290000
b11100 *
#1295000
b1100 *
#1500000
0#
#1750000
b11100011111101101101011110001111010010 $
b1100 (
b1100 ,
1#
#1780000
b11100011111101101101011110001111001110 +
b1000 *
#1785000
b11100011111101101101011110001111011110 +
b0 *
#1790000
b11100011111101101101011110001111111110 +
#1795000
x&
b11100011111101101101011110001111011110 +
b10000 *
#1805000
0&
#2000000
0#
#2250000
b10000 (
b10000 ,
b100101111111100111100101000010100011000 $
1#
#2280000
b100101111111100111100101000010100001000 +
b1100 *
#2285000
b100101111111100111100101000010100101000 +
b100 *
#2290000
b110100 *
#2300000
b10100 *
#2500000
0#
#2750000
b101111011111100001011110010011001011110 $
b10100 (
b10100 ,
1#
#2780000
b101111011111100001011110010011001101010 +
b10000 *
#2785000
b101111011111100001011110010011001100010 +
b11000 *
#2795000
b101111011111100001011110010011001110010 +
#3000000
0#
#3250000
b11000 (
b11000 ,
b111000111111011011010111100011110100100 $
1#
#3280000
b111000111111011011010111100011110000100 +
b10100 *
#3285000
b111000111111011011010111100011110101100 +
b11100 *
#3290000
b111000111111011011010111100011111001100 +
b1100 *
#3295000
b111000111111011011010111100011110011100 +
b11100 *
#3300000
b111000111111011011010111100011111011100 +
b111100 *
#3305000
b111000111111011011010111100011111111100 +
b11100 *
#3315000
b111000111111011011010111100011110111100 +
#3500000
0#
#3750000
b1000010011111010101010000110100011101010 $
b11100 (
b11100 ,
1#
#3780000
b1000010011111010101010000110100011110110 +
b11000 *
#3785000
b1000010011111010101010000110100011100110 +
b10000 *
#3795000
b1000010011111010101010000110100011000110 +
b0 *
#3805000
x&
b1000010011111010101010000110100010000110 +
b100000 *
#3815000
0&
b1000010011111010101010000110100000000110 +
#3825000
b1000010011111010101010000110100100000110 +
#4000000
0#
#4250000
b100000 (
b100000 ,
b1001011111111001111001010000101000110000 $
1#
#4280000
b1001011111111001111001010000101111100000 +
b11100 *
#4285000
b1001011111111001111001010000101111110000 +
b10100 *
#4290000
b1001011111111001111001010000101001110000 +
b1100100 *
#4295000
b1001011111111001111001010000101001010000 +
#4300000
b100100 *
#4500000
0#
#4750000
b1010101011111001001000011010101101110110 $
b100100 (
b100100 ,
1#
#4780000
b1010101011111001001000011010101100010010 +
b100000 *
#4785000
b1010101011111001001000011010101100011010 +
b101000 *
#4790000
b1010101011111001001000011010101110011010 +
#5000000
0#
#5250000
b101000 (
b101000 ,
b1011110111111000010111100100110010111100 $
1#
#5280000
b1011110111111000010111100100110001011100 +
b100100 *
#5285000
b1011110111111000010111100100110001000100 +
b101100 *
#5290000
b1011110111111000010111100100110111000100 +
b111100 *
#5295000
b1011110111111000010111100100110111100100 +
b101100 *
#5300000
b1011110111111000010111100100110011100100 +
#5500000
0#
#5750000
1"
b101100 (
b101100 ,
1#
#5780000
b1011110111111000010111100100110011100000 +
b101000 *
#5785000
b1011110111111000010111100100110011101000 +
b100000 *
#5795000
b110000 *
#6000000
0#
#6250000
b1011110111111000010111100100110011101000 (
b1011110111111000010111100100110011101000 ,
1#
#6280000
b101100 +
b1011110111111000010111100100110011110100 *
#6285000
b10111101111110000101111001001100100100100 +
b1011110111111000010111100100110011111100 *
#6290000
b10111101111110000101111001001100110100100 +
#6295000
b1011110111111000010111100100110011101100 *
#6500000
0#
#6750000
b10111101111110000101111001001100110100100 (
b10111101111110000101111001001100110100100 ,
1#
#6780000
b1011110111111000010111100100110011101000 +
b10111101111110000101111001001100110100000 *
#6785000
b11011010111101000110110101100010011110000 +
b10111101111110000101111001001100110101000 *
#6790000
b110011000111101001100110111110011001110000 +
#6795000
b10011000111101000100110101110011001000000 +
#6800000
b11100111101000000110101110011001000000 +
#6805000
b11100111101000000110101110011001100000 +
#6810000
b100011100111101001000110101110011001100000 +
#7000000
0#
#7250000
b100011100111101001000110101110011001100000 (
b100011100111101001000110101110011001100000 ,
1#
#7280000
b10111101111110000101111001001100110100100 +
b100011100111101001000110101110011001101100 *
#7285000
b10111101111000000101100000000000010101100 +
b100011100111101001000110101110011001100100 *
#7290000
b1111111111111000011111100000110011000101100 +
#7295000
b1111111111111100011111110010111011000111100 +
#7300000
b101111011111100001011110010011001100111100 +
#7305000
b101111011111100001011110010011001100011100 +
#7500000
0#
#7750000
b101111011111100001011110010011001100011100 (
b101111011111100001011110010011001100011100 ,
1#
#7780000
b100011100111101001000110101110011001100000 +
b101111011111100001011110010011001100011000 *
#7785000
b110010000111111001100111100110111000011000 +
b101111011111100001011110010011001100010000 *
#7790000
b111010010111111001110111010100110010011000 +
#7795000
b111011010111011001110101010101110011011000 +
b101111011111100001011110010011001100000000 *
#7800000
b111011010111011001110100110001100111011000 +
#7805000
b111011010111011001110100110011100111011000 +
b101111011111100001011110010011001100100000 *
#7810000
b111011010111011001110111111011001111011000 +
#7815000
b111011010111011001110111111111001111011000 +
#7820000
b111011010111011001110101111110011111011000 +
#7825000
b111011010111011001110101110110011111011000 +
#7830000
b111011010111011001110101110100111111011000 +
#7840000
b111011010111011001110101110001111111011000 +
#7850000
b111011010111011001110101111011111111011000 +
#7860000
b111011010111011001110101111111111111011000 +
#7870000
b111011010111011001110101110111111111011000 +
#8000000
0#
#8250000
b111011010111011001110101110111111111011000 (
b111011010111011001110101110111111111011000 ,
1#
#8280000
b101111011111100001011110010011001100011100 +
b111011010111011001110101110111111111100100 *
#8285000
b101111011110010001011001011010101000010100 +
b111011010111011001110101110111111111101100 *
#8290000
b111001110010000001001011010101010010100 +
#8295000
b111001111010000001101011000100010010100 +
b111011010111011001110101110111111111111100 *
#8300000
b1000111001111010010001101011000100010010100 +
#8305000
b1000111001111010010001101011100110010010100 +
b111011010111011001110101110111111111011100 *
#8500000
0#
#8750000
b1000111001111010010001101011100110010010100 (
b1000111001111010010001101011100110010010100 ,
1#
#8780000
b111011010111011001110101110111111111011000 +
b1000111001111010010001101011100110010010000 *
#8785000
b101011110111001001010100110111111111000000 +
b1000111001111010010001101011100110010011000 *
#8790000
b11000011100111001110000100100001100101000000 +
#8795000
b11000010100111001110000100100001100101010000 +
#8800000
b1010010000111001010100100000001100101010000 +
#8810000
b1010011000111001010100101000001100101010000 +
#9000000
0#
#9250000
b1010011000111001010100101000001100101010000 (
b1010011000111001010100101000001100101010000 ,
1#
#9280000
b1000111001111010010001101011100110010010100 +
b1010011000111001010100101000001100101011100 *
#9285000
b1000111001111100010001101010100010110011100 +
b1010011000111001010100101000001100101010100 *
#9290000
b1101111011111100011011101100110011100011100 +
#9295000
b1101111011110000011011101100110010100001100 +
#9300000
b1111111111110000011111100100110010000001100 +
#9305000
b1111111111111000011111100100110010000001100 +
#9310000
b1011110111111000010111100100110011000001100 +
#9500000
0#
#9750000
b1011110111111000010111100100110011000001100 (
b1011110111111000010111100100110011000001100 ,
1#
#9780000
b1010011000111001010100101000001100101010000 +
b1011110111111000010111100100110011000001000 *
#9785000
b1000000100111011010000110001000000101101000 +
b1011110111111000010111100100110011000000000 *
#9790000
b1001000110111011010010110001110011111101000 +
#9795000
b1101010110111111011010000001111011110001000 +
b1011110111111000010111100100110011000010000 *
#9800000
b1101010110111111011010000001011001010001000 +
#9805000
b1101010110110111011010100001011001011001000 +
#10000000
0#
#10250000
b1101010110110111011010100001011001011001000 (
b1101010110110111011010100001011001011001000 ,
1#
#10280000
b1011110111111000010111100100110011000001100 +
b1101010110110111011010100001011001011010100 *
#10285000
b1011110111100110010111101101110111100000100 +
b1101010110110111011010100001011001011011100 *
#10290000
b110110101100110001101101111100111110000100 +
#10295000
b110110101110110001101111101101111110000100 +
b1101010110110111011010100001011001011001100 *
#10300000
b11110110101110110111101111101001111110000100 +
#10305000
b11110110101110110111101011101011111110000100 +
#10310000
b1110110101110110011101011100011111110000100 +
#10315000
b1110110101110110011101011100111111110000100 +
#10320000
b1110110101110110011101011110111111110000100 +
#10325000
b1110110101110110011101011111111111110000100 +
#10335000
b1110110101110110011101011101111111110000100 +
